{
    "@type": "Workflow",
    "triggerLimit": null,
    "name": "Indicator (Type IP) - Get Reputation",
    "aliasName": null,
    "tag": "#Subroutine",
    "description": "Get Reputation of IP address",
    "isActive": true,
    "debug": false,
    "singleRecordExecution": false,
    "remoteExecutableFlag": false,
    "parameters": [
        "indicator_value"
    ],
    "synchronous": false,
    "collection": "\/api\/3\/workflow_collections\/deaa4d19-7444-4f3a-a80e-9577436f25ef",
    "versions": [],
    "triggerStep": "\/api\/3\/workflow_steps\/ae3bfdbd-6f64-4cba-a1b3-ae424e217f94",
    "steps": [
        {
            "@type": "WorkflowStep",
            "name": "Set Malicious",
            "description": null,
            "arguments": {
                "Reputation_Type_IRI": "{{(\"IndicatorReputation\" | picklist(\"Malicious\"))[\"@id\"]}}",
                "Reputation_Type_Text": "Malicious"
            },
            "status": null,
            "top": "190",
            "left": "3050",
            "stepType": "\/api\/3\/workflow_step_types\/04d0cf46-b6a8-42c4-8683-60a7eaa69e8f",
            "uuid": "ac6cdfa8-7eaa-4cbb-a179-d31b684a67b1"
        },
        {
            "@type": "WorkflowStep",
            "name": "Set Good",
            "description": null,
            "arguments": {
                "Reputation_Type_IRI": "{{(\"IndicatorReputation\" | picklist(\"Good\"))[\"@id\"]}}",
                "Reputation_Type_Text": "Good"
            },
            "status": null,
            "top": "350",
            "left": "3050",
            "stepType": "\/api\/3\/workflow_step_types\/04d0cf46-b6a8-42c4-8683-60a7eaa69e8f",
            "uuid": "0bb8c4ec-37f1-4d27-840b-db2914ac1fb0"
        },
        {
            "@type": "WorkflowStep",
            "name": "Get Reputation from MxToolbox",
            "description": null,
            "arguments": {
                "name": "MxToolbox",
                "config": "aa41f424-4472-4f04-aeec-0a17d6df45f8",
                "params": {
                    "value": "{{vars.record}}",
                    "object": "blacklist",
                    "api_method": "Lookup"
                },
                "version": "1.0.0",
                "connector": "mxtoolbox",
                "operation": "api_call",
                "ignore_errors": true,
                "operationTitle": "Get MxToolbox Records",
                "step_variables": {
                    "foundIPMxReputation": "{{ ( vars.result.data and (vars.result.data | length > 0) ) | ternary(true,false) }}"
                }
            },
            "status": null,
            "top": "670",
            "left": "2075",
            "stepType": "\/api\/3\/workflow_step_types\/0bfed618-0316-11e7-93ae-92361f002671",
            "uuid": "73e8482b-1768-45ba-aae9-20178d3bef98"
        },
        {
            "@type": "WorkflowStep",
            "name": "Summary",
            "description": null,
            "arguments": {
                "country": "{%if vars.steps.Geo_Locate_IP.data[0].location['country_flag']%}\n<center><span style=\"float: center;\"><img src=\"{{vars.steps.Geo_Locate_IP.data[0].location['country_flag']}}\" width=\"25\" ><\/span><\/center>\n{%endif%}",
                "reputation": "{{vars.Reputation_Type_Text}}",
                "reputation_iri": "{{vars.Reputation_Type_IRI}}",
                "enrichment_summary": "{{vars.steps.Enrichment_Summary.data['formatted_string']}}"
            },
            "status": null,
            "top": "430",
            "left": "4025",
            "stepType": "\/api\/3\/workflow_step_types\/04d0cf46-b6a8-42c4-8683-60a7eaa69e8f",
            "uuid": "7ace3f9f-0dc3-4144-a385-75197039b826"
        },
        {
            "@type": "WorkflowStep",
            "name": "Get Reputation from AlienVault OTX",
            "description": null,
            "arguments": {
                "name": "AlienVault-OTX",
                "config": "3d96900a-f870-4ac6-94d0-00865dbaf86f",
                "params": {
                    "page": 1,
                    "limit": 5,
                    "user_text": "{{vars.record}}"
                },
                "version": "1.0.0",
                "connector": "alienvault-otx",
                "operation": "search_pulses",
                "ignore_errors": true,
                "operationTitle": "Search Pulses",
                "step_variables": {
                    "foundAVReputation": "{{ ( vars.result.data.results and vars.result.data.results|json_query(\"[*].tags[]\") | length > 0 ) | ternary(true,false) }}"
                }
            },
            "status": null,
            "top": "30",
            "left": "2075",
            "stepType": "\/api\/3\/workflow_step_types\/0bfed618-0316-11e7-93ae-92361f002671",
            "uuid": "32214cae-5a7e-4d0b-932b-f317d8998020"
        },
        {
            "@type": "WorkflowStep",
            "name": "Get IP Reputation from Anomali",
            "description": null,
            "arguments": {
                "name": "Anomali ThreatStream",
                "config": "d5bbd0d1-2955-4705-a9a6-e7c1289e09d0",
                "params": {
                    "limit": 20,
                    "value": "{{vars.record}}",
                    "offset": 0,
                    "validation": false,
                    "filter_option": "Exact",
                    "record_number": "Fetch Limited Records"
                },
                "version": "2.2.1",
                "connector": "threatstream",
                "operation": "ip_reputation",
                "ignore_errors": true,
                "operationTitle": "Get IP Reputation",
                "pickFromTenant": false,
                "step_variables": {
                    "foundAnomaliReputation": "{{ ( vars.result.data.objects and vars.result.data.objects | length > 0 ) | ternary(true,false) }}"
                }
            },
            "status": null,
            "top": "190",
            "left": "2075",
            "stepType": "\/api\/3\/workflow_step_types\/0bfed618-0316-11e7-93ae-92361f002671",
            "uuid": "5fcdae05-6151-4884-a311-c62aa4cdd1e7"
        },
        {
            "@type": "WorkflowStep",
            "name": "Geo Locate IP",
            "description": null,
            "arguments": {
                "name": "IPStack",
                "config": "0022176c-57c0-4120-a8d2-ac03990bc318",
                "params": {
                    "query": "{{vars.record}}",
                    "fields": "",
                    "enable_hostname": false,
                    "enable_security": false
                },
                "version": "1.0.0",
                "connector": "ipstack",
                "operation": "ip_locate",
                "ignore_errors": true,
                "operationTitle": "Geolocate IP",
                "step_variables": {
                    "foundIpStackReputation": "{{ ( vars.result.data and (vars.result.data | length > 0) ) | ternary(true,false) }}"
                }
            },
            "status": null,
            "top": "350",
            "left": "2075",
            "stepType": "\/api\/3\/workflow_step_types\/0bfed618-0316-11e7-93ae-92361f002671",
            "uuid": "45c4b524-939d-4086-b4ae-9acd7946d292"
        },
        {
            "@type": "WorkflowStep",
            "name": "Configuration",
            "description": null,
            "arguments": {
                "record": "{{vars.input.params['indicator_value'] | ternary(vars.input.params['indicator_value'],vars.input.records[0].value) }}",
                "whoisdata_dict": "{}",
                "googleMapAPIkey": "AIzaSyDy4tlleelMlMRB-HuBbgxeBMrfUJQF2ZE",
                "foundIPMxReputation": "false",
                "foundAnomaliReputation": "false",
                "foundIpStackReputation": "false",
                "VT_reputation_threshold": "5"
            },
            "status": null,
            "top": "430",
            "left": "1100",
            "stepType": "\/api\/3\/workflow_step_types\/04d0cf46-b6a8-42c4-8683-60a7eaa69e8f",
            "uuid": "ea0a321d-5aac-4271-b2ee-89f3b5e2db54"
        },
        {
            "@type": "WorkflowStep",
            "name": "Compute AV OTX Summary",
            "description": null,
            "arguments": {
                "params": {
                    "value": "<p>{% if vars.foundAVReputation %}<\/p>\n<div class=\"font-size-11 ng-binding padding-bottom-sm\"><h4 style=\"background: #404142;padding: 5px;text-align: left;color: orange;background: black;\"> AlienVault OTX Summary<\/h4><\/div> \n<table style=\"width: 506px; border-color: #ffffff;\" border=\"1\">\n<tbody>\n<tr>\n<td style=\"width: 45px;font-size:16px;font-weight: normal\"><strong>Tags<\/strong><\/td>\n<td> <div class=\"font-size-14 font-weight-normal\">{{(vars.steps.Get_Reputation_from_AlienVault_OTX.data.results | json_query(\"[*].tags[]\") | unique | string).replace(\"[\",\"\").replace(\"]\",\"\")}}<\/div><\/td>\n<\/tr>\n<\/tbody>\n<\/table>\n<p>{% endif %}<\/p>\n"
                },
                "version": "3.1.1",
                "connector": "cyops_utilities",
                "operation": "format_richtext",
                "operationTitle": "Utils: Format as RichText",
                "step_variables": []
            },
            "status": null,
            "top": "30",
            "left": "2400",
            "stepType": "\/api\/3\/workflow_step_types\/0109f35d-090b-4a2b-bd8a-94cbc3508562",
            "uuid": "0346d1d9-7575-4ac0-b14b-190c725346fd"
        },
        {
            "@type": "WorkflowStep",
            "name": "Get Reputation from VT",
            "description": null,
            "arguments": {
                "name": "VirusTotal",
                "config": "8afd8a09-4f71-4cba-bb4e-31cd72da1a4e",
                "params": {
                    "ip": "{{vars.record}}",
                    "relationships": ""
                },
                "version": "2.2.0",
                "connector": "virustotal",
                "operation": "query_ip",
                "operationTitle": "Get IP Reputation",
                "pickFromTenant": false,
                "step_variables": {
                    "temp": "{% if vars.result.data.attributes.whois.raw %}{%- for item in vars.result.data.attributes.whois.raw[0].split(\"\\n\") -%}{%- set key = item.split(\":\")[0] -%}{%- set value = item.split(\":\")[1:] | join(\"\") -%}{%if value and key%}{{vars.whoisdata_dict.update({key:value})}}{%endif%}{%- endfor -%}{%endif%}",
                    "community_votes": "{{vars.result.data.attributes['total_votes']}}",
                    "last_analysis_stats": "{{vars.result.data.attributes['last_analysis_stats']}}"
                }
            },
            "status": null,
            "top": "840",
            "left": "1420",
            "stepType": "\/api\/3\/workflow_step_types\/0bfed618-0316-11e7-93ae-92361f002671",
            "uuid": "459be0f5-27d5-46c4-bcb8-afbad6c3457b"
        },
        {
            "@type": "WorkflowStep",
            "name": "Whois IP",
            "description": null,
            "arguments": {
                "name": "Whois RDAP",
                "config": "5f97d024-1ef2-4b73-b639-a2ec235f490d",
                "params": {
                    "ip": "{{vars.record}}"
                },
                "version": "1.0.0",
                "connector": "whois-rdap",
                "operation": "whois_ip",
                "ignore_errors": true,
                "operationTitle": "Whois IP",
                "step_variables": {
                    "foundWhoIsReputation": "{{ ( vars.result.data.asn_country_code and vars.result.data.asn_country_code | length > 0 ) | ternary(true,false) }}"
                }
            },
            "status": null,
            "top": "510",
            "left": "2075",
            "stepType": "\/api\/3\/workflow_step_types\/0bfed618-0316-11e7-93ae-92361f002671",
            "uuid": "53e4e7d7-8cba-4262-9714-3ad1a684ca5d"
        },
        {
            "@type": "WorkflowStep",
            "name": "Compute Private IP Summary",
            "description": null,
            "arguments": {
                "when": "{{vars.hostname != \"\"}}",
                "params": {
                    "value": "{% if vars.hostname %}\n<div class=\"card-container-body\" style=\"width: 280px;\">\n<div class=\"card-number\"><span class=\"card-count\">0<\/span>\n<div class=\"font-size-12 ng-binding\">Hostname: {{vars.hostname}}<\/div>\n{%else%}\n<div class=\"card-container-body\" style=\"width: 280px;\">\n<div class=\"card-number\"><span class=\"card-count\">0<\/span>\n<div class=\"font-size-12 ng-binding\">Hostname: Not Available <i class=\"icon icon-information margin-left-sm\" title=\"nslookup could not find hostname\"><\/i>\n<\/div>\n\n {%endif%}\n<div class=\"font-size-14 ng-binding\"><strong>Internal IP<\/strong><\/div>\n<\/div>\n<\/div>"
                },
                "version": "3.0.4",
                "connector": "cyops_utilities",
                "operation": "format_richtext",
                "operationTitle": "Utils: Format as RichText",
                "step_variables": []
            },
            "status": null,
            "top": "990",
            "left": "2725",
            "stepType": "\/api\/3\/workflow_step_types\/0109f35d-090b-4a2b-bd8a-94cbc3508562",
            "uuid": "b9df2dac-e03c-4e05-b8a5-f0673b4849ac"
        },
        {
            "@type": "WorkflowStep",
            "name": "Compute Anomali Summary",
            "description": null,
            "arguments": {
                "params": {
                    "value": "<p>{% if vars.foundAnomaliReputation %}<\/p>\n<div class=\"font-size-11 ng-binding padding-bottom-sm\"><h4 style=\"background: #404142;padding: 5px;text-align: left;color: orange;background: black;\"> Anomali Threatstream Detection Summary<\/h4><\/div>\n<div class=\"card-container-body\" style=\"width: 170px;\">\n{%if vars.steps.Get_IP_Reputation_from_Anomali.data.objects[0].threatscore !=0 %}\n<div class=\"card-number padding-top-sm padding-bottom-sm\" style=\" border-left: 5px solid red;background:#141b23\">\n <div class=\"line-height-1\"><a href=\"https:\/\/ui.threatstream.com\/detail\/domain\/{{vars.indicator_value}}\" target=\"_blank\" rel=\"noopener noreferrer\" class=\"font-size-8em\"> <span class=\"card-count\">{{vars.steps.Get_IP_Reputation_from_Anomali.data.objects[0].threatscore}} <\/span> <\/a>\n<div class=\"font-size-14 font-weight-normall padding-top-sm padding-bottom-sm\">Severity: {{vars.steps.Get_IP_Reputation_from_Anomali.data.objects[0].meta.severity}}<\/div>\n{%else%}\n<div class=\"card-number padding-top-sm padding-bottom-sm\" style=\" border-left: 5px solid red\">\n <div class=\"line-height-1\"><a href=\"https:\/\/ui.threatstream.com\/detail\/domain\/{{vars.indicator_value}}\" target=\"_blank\" rel=\"noopener noreferrer\" class=\"font-size-8em\"> <span class=\"card-count\">{{vars.steps.Get_IP_Reputation_from_Anomali.data.objects[0].threatscore}} <\/span> <\/a>\n<div class=\"font-size-14 font-weight-normall padding-top-sm padding-bottom-sm\">Severity: {{vars.steps.Get_IP_Reputation_from_Anomali.data.objects[0].meta.severity}}{% endif %}\n<\/div>\n\n<\/div>\n<\/div>\n<p>{% endif %}<\/p>\n"
                },
                "version": "3.1.1",
                "connector": "cyops_utilities",
                "operation": "format_richtext",
                "operationTitle": "Utils: Format as RichText",
                "step_variables": []
            },
            "status": null,
            "top": "190",
            "left": "2400",
            "stepType": "\/api\/3\/workflow_step_types\/0109f35d-090b-4a2b-bd8a-94cbc3508562",
            "uuid": "0e9e6e00-e08d-4428-b806-12b1cb53270d"
        },
        {
            "@type": "WorkflowStep",
            "name": "Is Referenced",
            "description": null,
            "arguments": {
                "conditions": [
                    {
                        "option": "Referenced",
                        "step_iri": "\/api\/3\/workflow_steps\/7ace3f9f-0dc3-4144-a385-75197039b826",
                        "condition": "{{ vars.input.params['indicator_value'] | length > 0 }}"
                    },
                    {
                        "option": "Upon Create",
                        "default": true,
                        "step_iri": "\/api\/3\/workflow_steps\/244fd4ce-94e2-49d9-9e02-1855868f39d3"
                    }
                ]
            },
            "status": null,
            "top": "510",
            "left": "3700",
            "stepType": "\/api\/3\/workflow_step_types\/12254cf5-5db7-4b1a-8cb1-3af081924b28",
            "uuid": "5813269a-9ce5-499a-9a71-bee8d800a5c0"
        },
        {
            "@type": "WorkflowStep",
            "name": "Compute VT Summary",
            "description": null,
            "arguments": {
                "params": {
                    "value": "<div class=\"font-size-11 ng-binding padding-bottom-sm\"><h4 style=\"background: #404142;padding: 5px;text-align: left;color: orange;background: black;\"> VirusTotal Detection Summary<\/h4><\/div>\n<table style=\"border-color: #04080c;\" border=\"1\" class=\"font-normal\">\n<tr><td style=\"border-color: #04080c;\">\n<table style=\"color:white;font-size:11;\" class=\"no-border\">\n<tr>\n<td>\n<html>\n  <head>\n    <title>Title of the document<\/title>\n    <style>\n      span.circle {\n        background: #2f3f51;\n        border-radius: 50%;\n        -moz-border-radius: 50%;\n        -webkit-border-radius: 50%;\n        display: inline-block;\n         font-weight: bold;\n        line-height: 100px;\n        margin-right: 5px;\n        text-align: center;\n        width: 100px;\n      font-size:15px;\n     border-color: Black;\n      }\n    <\/style>\n  <\/head>\n  <body><span class=\"circle\"><i style=\"font-size:25px;color:red \">\n   {{vars.last_analysis_stats.malicious}}<\/i>\/{{vars.last_analysis_stats.values() | list | sum}}<\/span>\n  <\/body>\n<\/html>\n<\/td>\n\n<td>\n<div class=\"font-size-14 ng-binding\">Malicious<\/div>\n<div class=\"card-container-body\" style=\"width: 100px;font-size:46px;\">\n<div class=\"card-number\"; style=\"font-size:45px;  border-left: 5px solid red;background:#141b23\">{{vars.last_analysis_stats.malicious}}<\/div>\n<\/div>\n<\/td>\n<td>\n<div class=\"font-size-14 ng-binding\">Suspicious<\/div>\n<div class=\"card-container-body\" style=\"width: 100px;\">\n<div class=\"card-number\" style=\"font-size:45px;  border-left: 5px solid orange; background:#141b23\">{{vars.last_analysis_stats.suspicious}}<\/div>\n<\/div>\n<\/td>\n<td>\n<div class=\"font-size-14 ng-binding\">Harmless<\/div>\n<div class=\"card-container-body\" style=\"width: 100px;\">\n<div class=\"card-number\" style=\"font-size:45px;  border-left: 5px solid green; background:#141b23\">{{vars.last_analysis_stats.harmless}}<\/div><\/div>\n<\/td>\n<\/tr>\n<\/table>\n\n<td style=\"vertical-align:top; border-color: #04080c;\">\n<table style=\"background-color: #1b2430; color:white;font-size:16;\" class=\"margin-10 no-border\">\n<tr>\n<div class=\"margin-top-md\">\n<i class=\"fa fa-group margin-left-md margin-right-sm\"><\/i> Community Votes<\/div>\n\n<td style=\"width: 100px;text-align: center;background:#141b23\">\n<i class=\"\tfa fa-thumbs-o-up\" style=\"font-size:25px;color:green\"><\/i>\n<div class=\"font-size-11 ng-binding\">Harmless {{vars.community_votes.harmless}}<\/div>\n<\/td>\n<td style=\"width: 100px;text-align: center;background:#141b23\">\n<i class=\"fa fa-thumbs-o-down\" style=\"font-size:25px;color:red \"><\/i>\n<div class=\"font-size-11 ng-binding\">Malicious {{vars.community_votes.malicious}}<\/div>\n<\/td>\n<\/tr>\n<\/table>\n<\/div>\n<\/td>\n<\/tr>\n<\/table>"
                },
                "version": "3.1.1",
                "connector": "cyops_utilities",
                "operation": "format_richtext",
                "operationTitle": "Utils: Format as RichText",
                "step_variables": {
                    "WhoisInformationVT": "{{vars.steps.Get_Reputation_from_VT.data.whois}}"
                }
            },
            "status": null,
            "top": "840",
            "left": "2080",
            "stepType": "\/api\/3\/workflow_step_types\/0109f35d-090b-4a2b-bd8a-94cbc3508562",
            "uuid": "41835230-9800-42fd-b963-3d89c1f3fe3b"
        },
        {
            "@type": "WorkflowStep",
            "name": "Set No Reputation for Private IP",
            "description": null,
            "arguments": {
                "Reputation_Type_IRI": "{{(\"IndicatorReputation\" | picklist(\"No Reputation Available\"))[\"@id\"]}}",
                "Reputation_Type_Text": "No Reputation Available"
            },
            "status": null,
            "top": "990",
            "left": "3050",
            "stepType": "\/api\/3\/workflow_step_types\/04d0cf46-b6a8-42c4-8683-60a7eaa69e8f",
            "uuid": "97033904-1b14-46ff-8467-52857bab2e93"
        },
        {
            "@type": "WorkflowStep",
            "name": "Set Suspicious",
            "description": null,
            "arguments": {
                "Reputation_Type_IRI": "{{(\"IndicatorReputation\" | picklist(\"Suspicious\"))[\"@id\"]}}",
                "Reputation_Type_Text": "Suspicious"
            },
            "status": null,
            "top": "830",
            "left": "3050",
            "stepType": "\/api\/3\/workflow_step_types\/04d0cf46-b6a8-42c4-8683-60a7eaa69e8f",
            "uuid": "e889fbe1-2864-4cd5-829b-e1a408e8047c"
        },
        {
            "@type": "WorkflowStep",
            "name": "Is IP Private",
            "description": null,
            "arguments": {
                "conditions": [
                    {
                        "option": "Public IP",
                        "default": true,
                        "step_iri": "\/api\/3\/workflow_steps\/ea0a321d-5aac-4271-b2ee-89f3b5e2db54",
                        "step_name": "Configuration"
                    },
                    {
                        "option": "Private IP",
                        "step_iri": "\/api\/3\/workflow_steps\/99db91d4-9524-46a1-b542-f90db517c6b0",
                        "condition": "{{ vars.steps.Match_IP_in_Internal_Subnets.data['matched_cidr_ip'] | length > 0 }}",
                        "step_name": "Find Hostname for Internal IP"
                    }
                ]
            },
            "status": null,
            "top": "740",
            "left": "780",
            "stepType": "\/api\/3\/workflow_step_types\/12254cf5-5db7-4b1a-8cb1-3af081924b28",
            "uuid": "26aeb7c8-d668-4ce7-aae3-78f2caa31f22"
        },
        {
            "@type": "WorkflowStep",
            "name": "Compute MxToolbox Summary",
            "description": null,
            "arguments": {
                "params": {
                    "value": "<p>{% if vars.foundIPMxReputation %}<\/p>\n<div class=\"font-size-11 ng-binding padding-bottom-sm\"><h4 style=\"background: #404142;padding: 5px;text-align: left;color: orange;background: black;\"> MXToolbox Summary<\/h4><\/div>\n<div class=\"card-container-body\" style=\"width: 200px;\">\n<div class=\"card-number \" style=\"font-size: 50px; font-weight: normal\"; class=\"font-size-8em\"><span class=\"card-count\">{{vars.steps.Get_Reputation_from_MxToolbox.data.result.MxRep}}<\/span>\n<div class=\"font-size-14 font-weight-normall padding-top-sm padding-bottom-sm\">{% if vars.steps.Get_Reputation_from_MxToolbox.data.result.MxRep == 100 %}Not blacklisted{%else%}Blacklisted{%endif%}<\/div>\n\n<\/div>\n<\/div>\n<p>{% endif %}&nbsp;<\/p>"
                },
                "version": "3.1.1",
                "connector": "cyops_utilities",
                "operation": "format_richtext",
                "ignore_errors": true,
                "operationTitle": "Utils: Format as RichText",
                "step_variables": []
            },
            "status": null,
            "top": "670",
            "left": "2400",
            "stepType": "\/api\/3\/workflow_step_types\/0109f35d-090b-4a2b-bd8a-94cbc3508562",
            "uuid": "6c3ca0e6-a296-43b9-94fd-4fd1af858b18"
        },
        {
            "@type": "WorkflowStep",
            "name": "Match IP in Internal Subnets",
            "description": null,
            "arguments": {
                "params": {
                    "cidr": "['10.0.0.0\/8','172.16.0.0\/12','192.168.0.0\/16']",
                    "ip_address": "{{vars.input.params['indicator_value'] | ternary(vars.input.params['indicator_value'],vars.input.records[0].value) }}"
                },
                "version": "2.7.0",
                "connector": "cyops_utilities",
                "operation": "ip_cidr_check",
                "operationTitle": "Utils: Is IP in CIDR",
                "step_variables": []
            },
            "status": null,
            "top": "740",
            "left": "480",
            "stepType": "\/api\/3\/workflow_step_types\/0109f35d-090b-4a2b-bd8a-94cbc3508562",
            "uuid": "181d8945-05a7-403c-bc43-d37c0632bfac"
        },
        {
            "@type": "WorkflowStep",
            "name": "Update Record",
            "description": null,
            "arguments": {
                "resource": {
                    "__link": {
                        "recordTags": "{% if vars.foundAVReputation %}{{(vars.steps.Get_Reputation_from_AlienVault_OTX.data.results | json_query(\"[*].tags[]\") | unique | string).replace(\"[\",\"\").replace(\"]\",\"\").replace(\"?\",\"\").replace(\"\\'\",\"\").replace(\"#\",\"\").replace(\"\\\"\",\"\").replace(\"\/\",\"\").replace(\"*\",\"\")}}{%endif%}"
                    },
                    "country": "{%if vars.steps.Geo_Locate_IP.data[0].location['country_flag']%}\n<center><span style=\"float: center\"; title=\"{{vars.steps.Geo_Locate_IP.data[0]['country_name']}}\";><img src=\"{{vars.steps.Geo_Locate_IP.data[0].location['country_flag']}}\" width=\"25\" ><\/span><\/center>\n{%endif%}\n",
                    "reputation": "{{vars.Reputation_Type_IRI}}",
                    "description": "{{vars.steps.Enrichment_Summary.data['formatted_string']}}\n"
                },
                "_showJson": false,
                "operation": "Overwrite",
                "collection": "{{vars.input.records[0]['@id']}}",
                "__recommend": [],
                "collectionType": "\/api\/3\/indicators",
                "fieldOperation": {
                    "recordTags": "Append"
                },
                "step_variables": []
            },
            "status": null,
            "top": "590",
            "left": "4025",
            "stepType": "\/api\/3\/workflow_step_types\/b593663d-7d13-40ce-a3a3-96dece928722",
            "uuid": "244fd4ce-94e2-49d9-9e02-1855868f39d3"
        },
        {
            "@type": "WorkflowStep",
            "name": "Set No Reputation",
            "description": null,
            "arguments": {
                "Reputation_Type_IRI": "{{(\"IndicatorReputation\" | picklist(\"No Reputation Available\"))[\"@id\"]}}",
                "Reputation_Type_Text": "No Reputation Available"
            },
            "status": null,
            "top": "670",
            "left": "3050",
            "stepType": "\/api\/3\/workflow_step_types\/04d0cf46-b6a8-42c4-8683-60a7eaa69e8f",
            "uuid": "982519a4-b10e-4807-83e8-c9a1d012fd3e"
        },
        {
            "@type": "WorkflowStep",
            "name": "Compute IP Stack Summary",
            "description": null,
            "arguments": {
                "params": {
                    "value": "<p>{% if vars.foundIpStackReputation %}<\/p>\n<div class=\"font-size-11 ng-binding padding-bottom-sm\">\n<h4 style=\"background: #404142;padding: 5px;text-align: left;color: orange;background: black;\"> IP Stack <\/h4><\/div>\n<table>\n<tbody>\n<tr>\n<td style=\"vertical-align: top;\">\n<p><span style=\"font-size: 10pt;\"><strong>{% if vars.foundIpStackReputation%}<\/strong><\/span><\/p>\n<div class=\"font-size-17 margin-top-12 padding-bottom-sm padding-left-sm\"><strong>Location Summary:<\/strong><\/div> \n<table style=\"width: 506px;\" border=\"1\" >\n<tbody>\n<tr style=\"height: 16px;\">\n<td style=\"border: 1px solid white; text-align: left; width: 135px; height: 16px;\"><span style=\"font-size: 10pt;\">Country<\/span><\/td>\n<td style=\"border: 1px solid white; text-align: left; width: 370px; height: 16px;\"><span style=\"font-size: 10pt;\">{{vars.steps.Geo_Locate_IP.data[0]['country_name']}}<\/span><\/td>\n<\/tr>\n<tr style=\"height: 16px;\">\n<td style=\"border: 1px solid white; text-align: left; width: 135px; height: 16px;\"><span style=\"font-size: 10pt;\">City<\/span><\/td>\n<td style=\"border: 1px solid white; text-align: left; width: 370px; height: 16px;\"><span style=\"font-size: 10pt;\">{{vars.steps.Geo_Locate_IP.data[0].city}}<\/span><\/td>\n<\/tr>\n<tr style=\"height: 16.9034px;\">\n<td style=\"border: 1px solid white; text-align: left; width: 135px; height: 16px;\"><span style=\"font-size: 10pt;;\">Latitude<\/span><\/td>\n<td style=\"border: 1px solid white; text-align: left; width: 370px; height: 16px;\"><span style=\"font-size: 10pt;\">{{vars.steps.Geo_Locate_IP.data[0].latitude}}<\/span><\/td>\n<\/tr>\n<tr style=\"height: 16.9034px;\">\n<td style=\"border: 1px solid white; text-align: left; width: 135px; height: 16px;\"><span style=\"font-size: 10pt;\">Longitude<\/span><\/td>\n<td style=\"border: 1px solid white; text-align: left; width: 370px; height: 16px;\"><span style=\"font-size: 10pt;\">{{vars.steps.Geo_Locate_IP.data[0].longitude}}<\/span><\/td>\n<\/tr>\n<\/tbody>\n<\/table>\n<td>\n\n<div class=\"font-size-17  padding-bottom-sm\"><strong>Map Location <\/strong><\/div>\n<img src=\"https:\/\/maps.googleapis.com\/maps\/api\/staticmap?key={{vars.googleMapAPIkey}}&center={{vars.steps.Geo_Locate_IP.data[0].latitude}},{{vars.steps.Geo_Locate_IP.data[0].longitude}}&zoom=13&format=png&maptype=roadmap&style=element:geometry|color:0x242f3e&style=element:labels.text.fill|color:0x746855&style=element:labels.text.stroke|color:0x242f3e&style=feature:administrative.locality|element:labels.text.fill|color:0xd59563&style=feature:poi|element:labels.text.fill|color:0xd59563&style=feature:poi.park|element:geometry|color:0x263c3f&style=feature:poi.park|element:labels.text.fill|color:0x6b9a76&style=feature:road|element:geometry|color:0x38414e&style=feature:road|element:geometry.stroke|color:0x212a37&style=feature:road|element:labels.text.fill|color:0x9ca5b3&style=feature:road.highway|element:geometry|color:0x746855&style=feature:road.highway|element:geometry.stroke|color:0x1f2835&style=feature:road.highway|element:labels.text.fill|color:0xf3d19c&style=feature:transit|element:geometry|color:0x2f3948&style=feature:transit.station|element:labels.text.fill|color:0xd59563&style=feature:water|element:geometry|color:0x17263c&style=feature:water|element:labels.text.fill|color:0x515c6d&style=feature:water|element:labels.text.stroke|color:0x17263c&size=600x300&markers=size:mid|color:0xff0000|label:|{{vars.steps.Geo_Locate_IP.data[0].latitude}},{{vars.steps.Geo_Locate_IP.data[0].longitude}}\" alt=\"\" width=\"500px\" height=\"300\" \/>\n{% endif %}\n<\/td>\n<\/tr>\n<\/tbody>\n<\/table>\n{% endif %}\n"
                },
                "version": "3.1.2",
                "connector": "cyops_utilities",
                "operation": "format_richtext",
                "operationTitle": "Utils: Format as RichText",
                "step_variables": []
            },
            "status": null,
            "top": "340",
            "left": "2400",
            "stepType": "\/api\/3\/workflow_step_types\/0109f35d-090b-4a2b-bd8a-94cbc3508562",
            "uuid": "e8a3c27e-ef24-45a4-a5cf-b9db9e700523"
        },
        {
            "@type": "WorkflowStep",
            "name": "Enrichment Summary",
            "description": null,
            "arguments": {
                "params": {
                    "value": "{% if vars.steps.Match_IP_in_Internal_Subnets.data['ip_matched'] %}<!--\n-->{{vars.steps.Compute_Private_IP_Summary.data['formatted_string']}}\n{% else %}\n{{vars.steps.Compute_VT_Summary.data['formatted_string']}}\n{% endif %}       \n\n{{vars.steps.Compute_Anomali_Summary.data['formatted_string']}}    \n\n{{vars.steps.Compute_IP_Stack_Summary.data['formatted_string']}}\n\n{{vars.steps.Compute_AV_OTX_Summary.data['formatted_string']}}\n      \n{{vars.steps.Compute_MxToolbox_Summary.data['formatted_string']}}\n \n{{vars.steps.Compute_VT_Whois.data['formatted_string']}}\n\n\n\n"
                },
                "version": "3.1.1",
                "connector": "cyops_utilities",
                "operation": "format_richtext",
                "operationTitle": "Utils: Format as RichText",
                "step_variables": []
            },
            "status": null,
            "top": "510",
            "left": "3375",
            "stepType": "\/api\/3\/workflow_step_types\/0109f35d-090b-4a2b-bd8a-94cbc3508562",
            "uuid": "54c7eaa7-c74e-40b9-b09e-16c350204e98"
        },
        {
            "@type": "WorkflowStep",
            "name": "Whois Information from VT",
            "description": null,
            "arguments": {
                "when": "{{(vars.whoisdata_dict | length > 0)}}",
                "params": {
                    "data": "{{vars.whoisdata_dict}}",
                    "styling": true,
                    "row_fields": "",
                    "table_style": "{ 'width':'auto','font':'10px;'}"
                },
                "version": "3.1.2",
                "connector": "cyops_utilities",
                "operation": "json_to_html",
                "operationTitle": "Utils: Convert JSON into a HTML Table",
                "step_variables": []
            },
            "status": null,
            "top": "840",
            "left": "1740",
            "stepType": "\/api\/3\/workflow_step_types\/0109f35d-090b-4a2b-bd8a-94cbc3508562",
            "uuid": "20554a8f-87d3-4bf6-971c-96b906158a85"
        },
        {
            "@type": "WorkflowStep",
            "name": "Compute Whois Summary",
            "description": null,
            "arguments": {
                "params": {
                    "value": "{% if vars.foundWhoIsReputation %}<div class=\"font-size-11 ng-binding padding-bottom-sm\"><h4 style=\"background: #404142;padding: 5px;text-align: left;color: orange;background: black;\">Whois IP Summary<\/h4><\/div>\n<table style=\"width: 500px;\" border=\"\\&quot;1\\&quot;\">\n<tbody>\n<tr>\n<td style=\"width: 100px;\"><strong>asn_country_code<\/strong><\/td>\n<td style=\"width: 400px;\">{{vars.steps.Whois_IP.data['asn_country_code']}}<\/td>\n<\/tr>\n<tr>\n<th style=\"width: 100px;\">entities<\/th>\n<td style=\"width: 400px;\">{% for value in vars.steps.Whois_IP.data.entities %} {{value}}<br \/>{%endfor%}<\/td>\n<\/tr>\n<tr>\n<th style=\"width: 100px;\">asn<\/th>\n<td style=\"width: 400px;\">{{vars.steps.Whois_IP.data.asn}}<\/td>\n<\/tr>\n<tr>\n<th style=\"width: 100px;\">asn_date<\/th>\n<td style=\"width: 400px;\">{{vars.steps.Whois_IP.data['asn_date']}}<\/td>\n<\/tr>\n<tr>\n<th style=\"width: 100px;\">asn_description<\/th>\n<td style=\"width: 400px;\">{{vars.steps.Whois_IP.data['asn_description']}}<\/td>\n<\/tr>\n<tr>\n<th style=\"width: 100px;\">asn_cidr<\/th>\n<td style=\"width: 400px;\">{{vars.steps.Whois_IP.data['asn_cidr']}}<\/td>\n<\/tr>\n<tr>\n<th style=\"width: 100px;\">objects<\/th>\n<td style=\"width: 400px;\">roles: {% for value in vars.steps.Whois_IP.data.objects[0].roles %} {{value}}&nbsp;<br \/>{%endfor%}<\/td>\n<\/tr>\n<tr>\n<th style=\"width: 150px;\">entities<\/th>\n<td style=\"width: 400px;\">{% for value in vars.steps.Whois_IP.data.entities %} {{value}} {%endfor%}<\/td>\n<\/tr>\n<\/tbody>\n<\/table>\n<p><br \/>{% endif %}<\/p>"
                },
                "version": "3.1.1",
                "connector": "cyops_utilities",
                "operation": "format_richtext",
                "operationTitle": "Utils: Format as RichText",
                "step_variables": []
            },
            "status": null,
            "top": "510",
            "left": "2400",
            "stepType": "\/api\/3\/workflow_step_types\/0109f35d-090b-4a2b-bd8a-94cbc3508562",
            "uuid": "6b7fafe2-e429-4cb5-aa1a-104db00f033b"
        },
        {
            "@type": "WorkflowStep",
            "name": "Get Hostname",
            "description": null,
            "arguments": {
                "name": "SSH",
                "config": "678f6a22-c999-4fd4-b18a-f8ae308c0762",
                "params": {
                    "cmd": "nslookup {{vars.input.params['indicator_value'] | ternary(vars.input.params['indicator_value'],vars.input.records[0].value) }}",
                    "allowed_exit": "-1,0",
                    "is_super_user": false
                },
                "version": "2.1.1",
                "connector": "ssh",
                "operation": "run_remote_command",
                "ignore_errors": true,
                "operationTitle": "Execute remote command",
                "step_variables": {
                    "hostname": "{{vars.result.data | regex_search('(?<=name = )(.*)')  | regex_replace('\\.(?!\\w)') | replace('\/\\\\r','') | trim}}"
                }
            },
            "status": null,
            "top": "990",
            "left": "2400",
            "stepType": "\/api\/3\/workflow_step_types\/0bfed618-0316-11e7-93ae-92361f002671",
            "uuid": "99db91d4-9524-46a1-b542-f90db517c6b0"
        },
        {
            "@type": "WorkflowStep",
            "name": "Compute VT Whois",
            "description": null,
            "arguments": {
                "params": {
                    "value": " \n{% if vars.steps.Get_Reputation_from_VT.data.attributes.whois.raw[0] != None and vars.steps.Get_Reputation_from_VT.data.attributes.whois.raw[0]  %}\n<div class=\"font-size-11 ng-binding padding-bottom-sm\"><h4 style=\"background: #404142;padding: 5px;text-align: left;color: orange;background: black;\">Additional Information<\/h4><\/div>\n<div class=\"font-size-17 padding-left-sm padding-bottom-sm\"><strong>Whois Information :<\/strong><\/div>\n   \n{{vars.steps.Whois_Information_from_VT.data}}{%endif%}<\/div>\n"
                },
                "version": "3.1.2",
                "connector": "cyops_utilities",
                "operation": "format_richtext",
                "operationTitle": "Utils: Format as RichText",
                "step_variables": {
                    "WhoisInformationVT": "{{vars.steps.Get_Reputation_from_VT.data.whois}}"
                }
            },
            "status": null,
            "top": "840",
            "left": "2400",
            "stepType": "\/api\/3\/workflow_step_types\/0109f35d-090b-4a2b-bd8a-94cbc3508562",
            "uuid": "39b39ba9-69ae-49c6-ae3b-b52c5dcee920"
        },
        {
            "@type": "WorkflowStep",
            "name": "Exit",
            "description": null,
            "arguments": {
                "params": [],
                "version": "3.2.1",
                "connector": "cyops_utilities",
                "operation": "no_op",
                "operationTitle": "Utils: No Operation",
                "step_variables": []
            },
            "status": null,
            "top": "740",
            "left": "40",
            "stepType": "\/api\/3\/workflow_step_types\/0109f35d-090b-4a2b-bd8a-94cbc3508562",
            "uuid": "5c9282c1-eec4-480b-ab4c-05ab3e9c2454"
        },
        {
            "@type": "WorkflowStep",
            "name": "Start",
            "description": "Indicator reputation is set as 'TBD' by 'Create and Link Indicator' utility playbook. We can ignore those indicators when triggering this PB",
            "arguments": {
                "resource": "indicators",
                "resources": [
                    "indicators"
                ],
                "step_variables": {
                    "input": {
                        "params": {
                            "indicator_value": "{{ vars.indicator_value }}"
                        },
                        "records": [
                            "{{vars.input.records[0]}}"
                        ]
                    }
                },
                "fieldbasedtrigger": {
                    "sort": [],
                    "limit": 30,
                    "logic": "AND",
                    "filters": [
                        {
                            "type": "object",
                            "field": "typeofindicator",
                            "value": "\/api\/3\/picklists\/c0beeda4-2c7a-4214-b7e5-53ba1649539c",
                            "_value": {
                                "@id": "\/api\/3\/picklists\/c0beeda4-2c7a-4214-b7e5-53ba1649539c",
                                "itemValue": "IP Address"
                            },
                            "operator": "eq"
                        },
                        {
                            "type": "object",
                            "field": "indicatorStatus",
                            "value": "\/api\/3\/picklists\/4218cb58-4de5-4eff-ad08-185d36ef9bab",
                            "_value": {
                                "@id": "\/api\/3\/picklists\/4218cb58-4de5-4eff-ad08-185d36ef9bab",
                                "itemValue": "Whitelisted"
                            },
                            "operator": "neq"
                        },
                        {
                            "logic": "OR",
                            "filters": [
                                {
                                    "type": "object",
                                    "field": "reputation",
                                    "value": "true",
                                    "_value": {
                                        "@id": "true",
                                        "display": "",
                                        "itemValue": ""
                                    },
                                    "operator": "isnull"
                                },
                                {
                                    "type": "object",
                                    "field": "reputation",
                                    "value": "\/api\/3\/picklists\/ae98ebc6-beef-4882-9980-1d88fc6d87cd",
                                    "_value": {
                                        "@id": "\/api\/3\/picklists\/ae98ebc6-beef-4882-9980-1d88fc6d87cd",
                                        "display": "TBD",
                                        "itemValue": "TBD"
                                    },
                                    "operator": "eq"
                                }
                            ]
                        }
                    ]
                }
            },
            "status": null,
            "top": "400",
            "left": "260",
            "stepType": "\/api\/3\/workflow_step_types\/ea155646-3821-4542-9702-b246da430a8d",
            "uuid": "ae3bfdbd-6f64-4cba-a1b3-ae424e217f94"
        },
        {
            "@type": "WorkflowStep",
            "name": "Is Dedicated Tenant Record",
            "description": null,
            "arguments": {
                "conditions": [
                    {
                        "option": "Yes, Enrich at Tenant Node",
                        "step_iri": "\/api\/3\/workflow_steps\/5c9282c1-eec4-480b-ab4c-05ab3e9c2454",
                        "condition": "{{ 'tenant' in vars.input.records[0] and vars.input.records[0].tenant.isDedicated and vars.input.records[0].tenant.role != 'self' }}",
                        "step_name": "Exit"
                    },
                    {
                        "option": "No, Enrich Here",
                        "default": true,
                        "step_iri": "\/api\/3\/workflow_steps\/181d8945-05a7-403c-bc43-d37c0632bfac",
                        "step_name": "Match IP in Internal Subnets"
                    }
                ]
            },
            "status": null,
            "top": "560",
            "left": "260",
            "stepType": "\/api\/3\/workflow_step_types\/12254cf5-5db7-4b1a-8cb1-3af081924b28",
            "uuid": "1761c731-f890-4d33-97f0-2d81a0a6ba92"
        },
        {
            "@type": "WorkflowStep",
            "name": "Is Malicious",
            "description": null,
            "arguments": {
                "conditions": [
                    {
                        "option": "Malicious",
                        "step_iri": "\/api\/3\/workflow_steps\/ac6cdfa8-7eaa-4cbb-a179-d31b684a67b1",
                        "condition": "{{ vars.last_analysis_stats.malicious > 0 }}",
                        "step_name": "Set Malicious"
                    },
                    {
                        "option": "Safe",
                        "step_iri": "\/api\/3\/workflow_steps\/0bb8c4ec-37f1-4d27-840b-db2914ac1fb0",
                        "condition": "{{ vars.last_analysis_stats.harmless > vars.last_analysis_stats.undetected }}",
                        "step_name": "Set Good"
                    },
                    {
                        "option": "No Reputation",
                        "default": true,
                        "step_iri": "\/api\/3\/workflow_steps\/982519a4-b10e-4807-83e8-c9a1d012fd3e",
                        "step_name": "Set No Reputation"
                    },
                    {
                        "option": "Suspicious",
                        "step_iri": "\/api\/3\/workflow_steps\/e889fbe1-2864-4cd5-829b-e1a408e8047c",
                        "condition": "{{ vars.last_analysis_stats.suspicious > 0 }}",
                        "step_name": "Set Suspicious"
                    }
                ]
            },
            "status": null,
            "top": "430",
            "left": "2725",
            "stepType": "\/api\/3\/workflow_step_types\/12254cf5-5db7-4b1a-8cb1-3af081924b28",
            "uuid": "25d259fb-8253-4a05-adcf-cc8b145f1da6"
        }
    ],
    "routes": [
        {
            "@type": "WorkflowRoute",
            "name": "Whois IP -> Compute Whois Summary",
            "targetStep": "\/api\/3\/workflow_steps\/6b7fafe2-e429-4cb5-aa1a-104db00f033b",
            "sourceStep": "\/api\/3\/workflow_steps\/53e4e7d7-8cba-4262-9714-3ad1a684ca5d",
            "label": null,
            "isExecuted": false,
            "uuid": "b9a004ce-7ca6-475f-ab74-18c6d0d2b1bf"
        },
        {
            "@type": "WorkflowRoute",
            "name": "ip -> Compute IP Stack Summary",
            "targetStep": "\/api\/3\/workflow_steps\/e8a3c27e-ef24-45a4-a5cf-b9db9e700523",
            "sourceStep": "\/api\/3\/workflow_steps\/45c4b524-939d-4086-b4ae-9acd7946d292",
            "label": null,
            "isExecuted": false,
            "uuid": "80578885-8c22-41d3-b969-e7fe913570a1"
        },
        {
            "@type": "WorkflowRoute",
            "name": "Get Reputation from Anomali -> Compute Anomali Summary",
            "targetStep": "\/api\/3\/workflow_steps\/0e9e6e00-e08d-4428-b806-12b1cb53270d",
            "sourceStep": "\/api\/3\/workflow_steps\/5fcdae05-6151-4884-a311-c62aa4cdd1e7",
            "label": null,
            "isExecuted": false,
            "uuid": "7835fda5-ebf2-4a53-bd5f-aedb6196b4ee"
        },
        {
            "@type": "WorkflowRoute",
            "name": "Get Reputation from MxToolbox -> Compute MxToolbox Summary",
            "targetStep": "\/api\/3\/workflow_steps\/6c3ca0e6-a296-43b9-94fd-4fd1af858b18",
            "sourceStep": "\/api\/3\/workflow_steps\/73e8482b-1768-45ba-aae9-20178d3bef98",
            "label": null,
            "isExecuted": false,
            "uuid": "addd2bee-b571-4d39-9750-ff29254f9a85"
        },
        {
            "@type": "WorkflowRoute",
            "name": "Check CIDR -> Is IP Private",
            "targetStep": "\/api\/3\/workflow_steps\/26aeb7c8-d668-4ce7-aae3-78f2caa31f22",
            "sourceStep": "\/api\/3\/workflow_steps\/181d8945-05a7-403c-bc43-d37c0632bfac",
            "label": null,
            "isExecuted": false,
            "uuid": "07394c31-e53d-4586-a8c6-64f5c3f217df"
        },
        {
            "@type": "WorkflowRoute",
            "name": "Is IP Private -> Configuration",
            "targetStep": "\/api\/3\/workflow_steps\/ea0a321d-5aac-4271-b2ee-89f3b5e2db54",
            "sourceStep": "\/api\/3\/workflow_steps\/26aeb7c8-d668-4ce7-aae3-78f2caa31f22",
            "label": "Public IP",
            "isExecuted": false,
            "uuid": "8b204741-2e2e-4952-836d-2c5e886e9204"
        },
        {
            "@type": "WorkflowRoute",
            "name": "Configuration -> Get Reputation from AlienVault OTX",
            "targetStep": "\/api\/3\/workflow_steps\/32214cae-5a7e-4d0b-932b-f317d8998020",
            "sourceStep": "\/api\/3\/workflow_steps\/ea0a321d-5aac-4271-b2ee-89f3b5e2db54",
            "label": null,
            "isExecuted": false,
            "uuid": "6ecb4b7f-a1dc-48c9-ae29-b87391d56830"
        },
        {
            "@type": "WorkflowRoute",
            "name": "Configuration -> Get Reputation from Anomali",
            "targetStep": "\/api\/3\/workflow_steps\/5fcdae05-6151-4884-a311-c62aa4cdd1e7",
            "sourceStep": "\/api\/3\/workflow_steps\/ea0a321d-5aac-4271-b2ee-89f3b5e2db54",
            "label": null,
            "isExecuted": false,
            "uuid": "0517a4de-fa0b-438c-9bd5-8125cbe6b202"
        },
        {
            "@type": "WorkflowRoute",
            "name": "Configuration -> Geo Locate IP",
            "targetStep": "\/api\/3\/workflow_steps\/45c4b524-939d-4086-b4ae-9acd7946d292",
            "sourceStep": "\/api\/3\/workflow_steps\/ea0a321d-5aac-4271-b2ee-89f3b5e2db54",
            "label": null,
            "isExecuted": false,
            "uuid": "f27f1d38-859b-409a-af1c-cfd2e7396c5d"
        },
        {
            "@type": "WorkflowRoute",
            "name": "Configuration -> Whois IP",
            "targetStep": "\/api\/3\/workflow_steps\/53e4e7d7-8cba-4262-9714-3ad1a684ca5d",
            "sourceStep": "\/api\/3\/workflow_steps\/ea0a321d-5aac-4271-b2ee-89f3b5e2db54",
            "label": null,
            "isExecuted": false,
            "uuid": "4af7cde7-76dd-4d4b-8a7e-ebaa5308bff2"
        },
        {
            "@type": "WorkflowRoute",
            "name": "Configuration -> Get Reputation from MxToolbox",
            "targetStep": "\/api\/3\/workflow_steps\/73e8482b-1768-45ba-aae9-20178d3bef98",
            "sourceStep": "\/api\/3\/workflow_steps\/ea0a321d-5aac-4271-b2ee-89f3b5e2db54",
            "label": null,
            "isExecuted": false,
            "uuid": "78c14a12-1c1e-499e-8df3-8e6641566152"
        },
        {
            "@type": "WorkflowRoute",
            "name": "Is Upon Create -> Summary",
            "targetStep": "\/api\/3\/workflow_steps\/7ace3f9f-0dc3-4144-a385-75197039b826",
            "sourceStep": "\/api\/3\/workflow_steps\/5813269a-9ce5-499a-9a71-bee8d800a5c0",
            "label": "Referenced",
            "isExecuted": false,
            "uuid": "a3c07e48-05a9-4ce5-95fd-dfa067bbe1eb"
        },
        {
            "@type": "WorkflowRoute",
            "name": "Is Upon Create -> Update Record",
            "targetStep": "\/api\/3\/workflow_steps\/244fd4ce-94e2-49d9-9e02-1855868f39d3",
            "sourceStep": "\/api\/3\/workflow_steps\/5813269a-9ce5-499a-9a71-bee8d800a5c0",
            "label": "Upon Create",
            "isExecuted": false,
            "uuid": "f896cf6c-cf5b-47a1-9a81-1b3a149aeeeb"
        },
        {
            "@type": "WorkflowRoute",
            "name": "Whois Data JSON to HTML -> Compute VT Summary",
            "targetStep": "\/api\/3\/workflow_steps\/41835230-9800-42fd-b963-3d89c1f3fe3b",
            "sourceStep": "\/api\/3\/workflow_steps\/20554a8f-87d3-4bf6-971c-96b906158a85",
            "label": null,
            "isExecuted": false,
            "uuid": "fae640e6-f3a2-46a6-bc89-db7fa940a109"
        },
        {
            "@type": "WorkflowRoute",
            "name": "Get Reputation from AlienVault OTX -> Compute AV OTX Summary",
            "targetStep": "\/api\/3\/workflow_steps\/0346d1d9-7575-4ac0-b14b-190c725346fd",
            "sourceStep": "\/api\/3\/workflow_steps\/32214cae-5a7e-4d0b-932b-f317d8998020",
            "label": null,
            "isExecuted": false,
            "uuid": "11d4c8f0-c3c9-479e-9cb1-b0d22297ecbe"
        },
        {
            "@type": "WorkflowRoute",
            "name": "Compute Private IP Summary -> Copy  of Set No Reputation",
            "targetStep": "\/api\/3\/workflow_steps\/97033904-1b14-46ff-8467-52857bab2e93",
            "sourceStep": "\/api\/3\/workflow_steps\/b9df2dac-e03c-4e05-b8a5-f0673b4849ac",
            "label": null,
            "isExecuted": false,
            "uuid": "f8db52bb-7353-431a-8f00-008e74c9e456"
        },
        {
            "@type": "WorkflowRoute",
            "name": "Is IP Private -> Find Hostname for Internal IP",
            "targetStep": "\/api\/3\/workflow_steps\/99db91d4-9524-46a1-b542-f90db517c6b0",
            "sourceStep": "\/api\/3\/workflow_steps\/26aeb7c8-d668-4ce7-aae3-78f2caa31f22",
            "label": "Private IP",
            "isExecuted": false,
            "uuid": "1b42e310-5a29-4b08-a452-83d8fe7d05a8"
        },
        {
            "@type": "WorkflowRoute",
            "name": "Find Hostname for Internal IP -> Compute Private IP Summary",
            "targetStep": "\/api\/3\/workflow_steps\/b9df2dac-e03c-4e05-b8a5-f0673b4849ac",
            "sourceStep": "\/api\/3\/workflow_steps\/99db91d4-9524-46a1-b542-f90db517c6b0",
            "label": null,
            "isExecuted": false,
            "uuid": "b3f97957-feb1-4f97-a2b8-549523492503"
        },
        {
            "@type": "WorkflowRoute",
            "name": "Configuration -> Get Reputation from VT",
            "targetStep": "\/api\/3\/workflow_steps\/459be0f5-27d5-46c4-bcb8-afbad6c3457b",
            "sourceStep": "\/api\/3\/workflow_steps\/ea0a321d-5aac-4271-b2ee-89f3b5e2db54",
            "label": null,
            "isExecuted": false,
            "uuid": "d52a1651-089e-462c-a257-5b8f8dfc17b8"
        },
        {
            "@type": "WorkflowRoute",
            "name": "Get Reputation from VT -> Whois Information from VT",
            "targetStep": "\/api\/3\/workflow_steps\/20554a8f-87d3-4bf6-971c-96b906158a85",
            "sourceStep": "\/api\/3\/workflow_steps\/459be0f5-27d5-46c4-bcb8-afbad6c3457b",
            "label": null,
            "isExecuted": false,
            "uuid": "71f9f94f-cb1c-47e9-913f-f14443a97378"
        },
        {
            "@type": "WorkflowRoute",
            "name": "Is Malicious -> Set Malicious",
            "targetStep": "\/api\/3\/workflow_steps\/ac6cdfa8-7eaa-4cbb-a179-d31b684a67b1",
            "sourceStep": "\/api\/3\/workflow_steps\/25d259fb-8253-4a05-adcf-cc8b145f1da6",
            "label": "Malicious",
            "isExecuted": false,
            "uuid": "617e0496-c5f9-4b48-9e8e-5d09b751b79a"
        },
        {
            "@type": "WorkflowRoute",
            "name": "Is Malicious -> Set Good",
            "targetStep": "\/api\/3\/workflow_steps\/0bb8c4ec-37f1-4d27-840b-db2914ac1fb0",
            "sourceStep": "\/api\/3\/workflow_steps\/25d259fb-8253-4a05-adcf-cc8b145f1da6",
            "label": "Safe",
            "isExecuted": false,
            "uuid": "70e417da-7a85-4ecd-8a8f-0d6b869165a5"
        },
        {
            "@type": "WorkflowRoute",
            "name": "Is Malicious -> Set No Reputation",
            "targetStep": "\/api\/3\/workflow_steps\/982519a4-b10e-4807-83e8-c9a1d012fd3e",
            "sourceStep": "\/api\/3\/workflow_steps\/25d259fb-8253-4a05-adcf-cc8b145f1da6",
            "label": "No Reputation",
            "isExecuted": false,
            "uuid": "5d56f481-679d-4751-8cb8-084c4ad76be4"
        },
        {
            "@type": "WorkflowRoute",
            "name": "Is Malicious -> Set Suspicious",
            "targetStep": "\/api\/3\/workflow_steps\/e889fbe1-2864-4cd5-829b-e1a408e8047c",
            "sourceStep": "\/api\/3\/workflow_steps\/25d259fb-8253-4a05-adcf-cc8b145f1da6",
            "label": "Suspicious",
            "isExecuted": false,
            "uuid": "a9e7696c-3cb3-4583-8c06-d6c7525973bc"
        },
        {
            "@type": "WorkflowRoute",
            "name": "Compute VT Summary -> Compute VT Whois",
            "targetStep": "\/api\/3\/workflow_steps\/39b39ba9-69ae-49c6-ae3b-b52c5dcee920",
            "sourceStep": "\/api\/3\/workflow_steps\/41835230-9800-42fd-b963-3d89c1f3fe3b",
            "label": null,
            "isExecuted": false,
            "uuid": "f744c0f1-3fa5-4c61-99d3-9644534a1f9b"
        },
        {
            "@type": "WorkflowRoute",
            "name": "Compute AV OTX Summary -> Is Malicious",
            "targetStep": "\/api\/3\/workflow_steps\/25d259fb-8253-4a05-adcf-cc8b145f1da6",
            "sourceStep": "\/api\/3\/workflow_steps\/0346d1d9-7575-4ac0-b14b-190c725346fd",
            "label": null,
            "isExecuted": false,
            "uuid": "26113fea-2b02-41ea-971c-fd880856b9e3"
        },
        {
            "@type": "WorkflowRoute",
            "name": "Compute Anomali Summary -> Is Malicious",
            "targetStep": "\/api\/3\/workflow_steps\/25d259fb-8253-4a05-adcf-cc8b145f1da6",
            "sourceStep": "\/api\/3\/workflow_steps\/0e9e6e00-e08d-4428-b806-12b1cb53270d",
            "label": null,
            "isExecuted": false,
            "uuid": "61ee4df5-c995-45d4-9a00-7af9f4c17faf"
        },
        {
            "@type": "WorkflowRoute",
            "name": "Compute IP Stack Summary -> Is Malicious",
            "targetStep": "\/api\/3\/workflow_steps\/25d259fb-8253-4a05-adcf-cc8b145f1da6",
            "sourceStep": "\/api\/3\/workflow_steps\/e8a3c27e-ef24-45a4-a5cf-b9db9e700523",
            "label": null,
            "isExecuted": false,
            "uuid": "b8bb407f-1cc6-4656-88fb-f6cf094e4a2e"
        },
        {
            "@type": "WorkflowRoute",
            "name": "Compute Whois Summary -> Is Malicious",
            "targetStep": "\/api\/3\/workflow_steps\/25d259fb-8253-4a05-adcf-cc8b145f1da6",
            "sourceStep": "\/api\/3\/workflow_steps\/6b7fafe2-e429-4cb5-aa1a-104db00f033b",
            "label": null,
            "isExecuted": false,
            "uuid": "cb2baf7e-fe96-4d51-8c09-4ef069d3b311"
        },
        {
            "@type": "WorkflowRoute",
            "name": "Compute MxToolbox Summary -> Is Malicious",
            "targetStep": "\/api\/3\/workflow_steps\/25d259fb-8253-4a05-adcf-cc8b145f1da6",
            "sourceStep": "\/api\/3\/workflow_steps\/6c3ca0e6-a296-43b9-94fd-4fd1af858b18",
            "label": null,
            "isExecuted": false,
            "uuid": "8a3f3688-a122-4c40-bce3-cc011373f841"
        },
        {
            "@type": "WorkflowRoute",
            "name": "Compute VT Whois -> Is Malicious",
            "targetStep": "\/api\/3\/workflow_steps\/25d259fb-8253-4a05-adcf-cc8b145f1da6",
            "sourceStep": "\/api\/3\/workflow_steps\/39b39ba9-69ae-49c6-ae3b-b52c5dcee920",
            "label": null,
            "isExecuted": false,
            "uuid": "f77944fc-1ac1-4596-828b-4765aeb361b1"
        },
        {
            "@type": "WorkflowRoute",
            "name": "Set Malicious -> Enrichment Summary",
            "targetStep": "\/api\/3\/workflow_steps\/54c7eaa7-c74e-40b9-b09e-16c350204e98",
            "sourceStep": "\/api\/3\/workflow_steps\/ac6cdfa8-7eaa-4cbb-a179-d31b684a67b1",
            "label": null,
            "isExecuted": false,
            "uuid": "2f73bb27-7d1b-4c57-b24d-1a555de148d4"
        },
        {
            "@type": "WorkflowRoute",
            "name": "Set Good -> Enrichment Summary",
            "targetStep": "\/api\/3\/workflow_steps\/54c7eaa7-c74e-40b9-b09e-16c350204e98",
            "sourceStep": "\/api\/3\/workflow_steps\/0bb8c4ec-37f1-4d27-840b-db2914ac1fb0",
            "label": null,
            "isExecuted": false,
            "uuid": "6b61dfd6-bad6-449b-a63f-c2fcc40758ce"
        },
        {
            "@type": "WorkflowRoute",
            "name": "Set No Reputation -> Enrichment Summary",
            "targetStep": "\/api\/3\/workflow_steps\/54c7eaa7-c74e-40b9-b09e-16c350204e98",
            "sourceStep": "\/api\/3\/workflow_steps\/982519a4-b10e-4807-83e8-c9a1d012fd3e",
            "label": null,
            "isExecuted": false,
            "uuid": "597c720a-c737-4ace-bddb-cad1bd3ff6f5"
        },
        {
            "@type": "WorkflowRoute",
            "name": "Set Suspicious -> Enrichment Summary",
            "targetStep": "\/api\/3\/workflow_steps\/54c7eaa7-c74e-40b9-b09e-16c350204e98",
            "sourceStep": "\/api\/3\/workflow_steps\/e889fbe1-2864-4cd5-829b-e1a408e8047c",
            "label": null,
            "isExecuted": false,
            "uuid": "40391f72-9136-44b9-aa83-211ecd87f799"
        },
        {
            "@type": "WorkflowRoute",
            "name": "Set No Reputation for Private IP -> Enrichment Summary",
            "targetStep": "\/api\/3\/workflow_steps\/54c7eaa7-c74e-40b9-b09e-16c350204e98",
            "sourceStep": "\/api\/3\/workflow_steps\/97033904-1b14-46ff-8467-52857bab2e93",
            "label": null,
            "isExecuted": false,
            "uuid": "fb9f6d09-8bc7-4feb-934e-5e58cbabca86"
        },
        {
            "@type": "WorkflowRoute",
            "name": "Enrichment Summary -> Is Referenced",
            "targetStep": "\/api\/3\/workflow_steps\/5813269a-9ce5-499a-9a71-bee8d800a5c0",
            "sourceStep": "\/api\/3\/workflow_steps\/54c7eaa7-c74e-40b9-b09e-16c350204e98",
            "label": null,
            "isExecuted": false,
            "uuid": "fbe6871b-d66b-4013-aa35-3e3f28ed904d"
        },
        {
            "@type": "WorkflowRoute",
            "name": "Has Dedicated Tenant Record -> Exit",
            "targetStep": "\/api\/3\/workflow_steps\/5c9282c1-eec4-480b-ab4c-05ab3e9c2454",
            "sourceStep": "\/api\/3\/workflow_steps\/1761c731-f890-4d33-97f0-2d81a0a6ba92",
            "label": "Yes, Enrich at Tenant Node",
            "isExecuted": false,
            "uuid": "6232284a-c661-4866-b597-9f501acbebf8"
        },
        {
            "@type": "WorkflowRoute",
            "name": "Start -> Has Dedicated Tenant Record",
            "targetStep": "\/api\/3\/workflow_steps\/1761c731-f890-4d33-97f0-2d81a0a6ba92",
            "sourceStep": "\/api\/3\/workflow_steps\/ae3bfdbd-6f64-4cba-a1b3-ae424e217f94",
            "label": null,
            "isExecuted": false,
            "uuid": "4b012477-454a-45d2-a5ec-37806d09c1d8"
        },
        {
            "@type": "WorkflowRoute",
            "name": "Has Dedicated Tenant Record -> Match IP in Internal Subnets",
            "targetStep": "\/api\/3\/workflow_steps\/181d8945-05a7-403c-bc43-d37c0632bfac",
            "sourceStep": "\/api\/3\/workflow_steps\/1761c731-f890-4d33-97f0-2d81a0a6ba92",
            "label": "No, Enrich Here",
            "isExecuted": false,
            "uuid": "4928c753-f8d0-4fb6-b01e-0b3b3b82df75"
        }
    ],
    "priority": null,
    "uuid": "d809cafc-edbc-4903-9d58-fe906ba8aea5",
    "owners": [],
    "isPrivate": false,
    "deletedAt": null,
    "recordTags": [
        "Subroutine"
    ]
}
