{
  "type": "workflow_collections",
  "data": [
    {
      "@context": "/api/3/contexts/WorkflowCollection",
      "@type": "WorkflowCollection",
      "name": "03 - Enrich",
      "description": null,
      "visible": true,
      "image": null,
      "id": 18,
      "createDate": 1649319945.015677,
      "modifyDate": 1649319945.015677,
      "deletedAt": null,
      "importedBy": [
        {
          "apiName": "sOARFramework",
          "name": "SOAR Framework",
          "version": "1.0.0"
        }
      ],
      "recordTags": [],
      "workflows": [
        {
          "@type": "Workflow",
          "triggerLimit": null,
          "name": "Indicator (Type Domain) - Get Reputation",
          "aliasName": null,
          "tag": "#Subroutine",
          "description": "Retrieves the reputation of indicators of type ‘Domain’ using configured threat intelligence tools.",
          "isActive": true,
          "debug": false,
          "singleRecordExecution": false,
          "remoteExecutableFlag": false,
          "parameters": [
            "indicator_value"
          ],
          "synchronous": false,
          "lastModifyDate": 1649319945,
          "collection": "/api/3/workflow_collections/bea2a6c5-c98d-4ee5-befd-9fbfd11c2a32",
          "versions": [],
          "triggerStep": "/api/3/workflow_steps/30c8d3ed-3507-4392-ba43-dfa2bf4105d0",
          "steps": [
            {
              "@type": "WorkflowStep",
              "name": "Update Record",
              "description": null,
              "arguments": {
                "resource": {
                  "__link": {
                    "recordTags": "{% if vars.foundAVReputation %}{{(vars.steps.Get_Reputation_from_AlienVault_OTX.data.results | json_query(\"[*].tags[]\") | unique | string).replace(\"[\",\"\").replace(\"]\",\"\").replace(\"?\",\"\").replace(\"\\'\",\"\").replace(\"#\",\"\").replace(\"\\\"\",\"\").replace(\"/\",\"\").replace(\"*\",\"\")}}{%endif%}"
                  },
                  "reputation": "{{vars.Reputation_Type_IRI}}",
                  "description": "{{vars.steps.Enrichment_Summary.data['formatted_string']}}"
                },
                "_showJson": false,
                "operation": "Overwrite",
                "collection": "{{vars.input.records[0]['@id']}}",
                "__recommend": [],
                "collectionType": "/api/3/indicators",
                "fieldOperation": {
                  "recordTags": "Append"
                },
                "step_variables": []
              },
              "status": null,
              "top": "430",
              "left": "4350",
              "stepType": "/api/3/workflow_step_types/b593663d-7d13-40ce-a3a3-96dece928722",
              "uuid": "02b321a1-a785-4f50-8e6d-d43637daa27d"
            },
            {
              "@type": "WorkflowStep",
              "name": "Get Reputation from AlienVault OTX",
              "description": null,
              "arguments": {
                "name": "AlienVault-OTX",
                "config": "3d96900a-f870-4ac6-94d0-00865dbaf86f",
                "params": {
                  "page": 1,
                  "limit": 5,
                  "user_text": "{{vars.indicator_value}}"
                },
                "version": "1.0.0",
                "connector": "alienvault-otx",
                "operation": "search_pulses",
                "ignore_errors": true,
                "operationTitle": "Search Pulses",
                "step_variables": {
                  "foundAVReputation": "{{ ( vars.result.data.results and vars.result.data.results | json_query(\"[*].tags[]\")  | length > 0 ) | ternary(true,false) }}"
                }
              },
              "status": null,
              "top": "350",
              "left": "2400",
              "stepType": "/api/3/workflow_step_types/0bfed618-0316-11e7-93ae-92361f002671",
              "uuid": "1afaa2be-453f-4b6d-8fb3-d574339d8580"
            },
            {
              "@type": "WorkflowStep",
              "name": "Is Dedicated Tenant Record",
              "description": null,
              "arguments": {
                "conditions": [
                  {
                    "option": "Yes, Enrich at Tenant Node",
                    "step_iri": "/api/3/workflow_steps/3e633ed1-31d8-418b-9ec4-a0352826adaa",
                    "condition": "{{ 'tenant' in vars.input.records[0] and vars.input.records[0].tenant.isDedicated and vars.input.records[0].tenant.role != 'self' }}",
                    "step_name": "Exit"
                  },
                  {
                    "option": "No, Enrich Here",
                    "default": true,
                    "step_iri": "/api/3/workflow_steps/c2e6cb54-8213-4f30-a6fc-b53712ad94e5",
                    "step_name": "Configuration"
                  }
                ]
              },
              "status": null,
              "top": "670",
              "left": "450",
              "stepType": "/api/3/workflow_step_types/12254cf5-5db7-4b1a-8cb1-3af081924b28",
              "uuid": "235eaa62-6990-40bb-ab83-8d0cea217942"
            },
            {
              "@type": "WorkflowStep",
              "name": "Get Domain Reputation from VT",
              "description": null,
              "arguments": {
                "name": "VirusTotal",
                "config": "1ba6a7ef-304a-4f78-855d-70b09bcd0b0a",
                "params": {
                  "domain": "{{vars.indicator_value}}",
                  "relationships": ""
                },
                "version": "2.2.0",
                "connector": "virustotal",
                "operation": "query_domain",
                "operationTitle": "Get Domain Reputation",
                "step_variables": {
                  "temp": "{% if vars.result.data.attributes.whois.raw %}{%- for item in vars.result.data.attributes.whois.raw[0].split(\"\\n\") -%}{%- set key = item.split(\":\")[0] -%}{%- set value = item.split(\":\")[1:] | join(\"\") -%}{%if value and key%}{{vars.whoisdata_dict.update({key:value})}}{%endif%}{%- endfor -%}{%endif%}",
                  "community_votes": "{{vars.result.data.attributes['total_votes']}}",
                  "last_analysis_stats": "{{vars.result.data.attributes['last_analysis_stats']}}"
                },
                "operationOutput": {
                  "scans": [],
                  "total": "",
                  "scan_id": "",
                  "resource": "",
                  "aggregate": "",
                  "permalink": "",
                  "positives": "",
                  "scan_date": "",
                  "verbose_msg": ""
                }
              },
              "status": null,
              "top": "990",
              "left": "1100",
              "stepType": "/api/3/workflow_step_types/0bfed618-0316-11e7-93ae-92361f002671",
              "uuid": "295a0467-b576-44c0-8cc8-5e812ed3c7d6"
            },
            {
              "@type": "WorkflowStep",
              "name": "Compute AV OTX Summary",
              "description": null,
              "arguments": {
                "params": {
                  "value": "<p>{% if vars.foundAVReputation %}</p>\n<div class=\"font-size-11 ng-binding padding-bottom-sm\"><h4 style=\"background: #404142;padding: 5px;text-align: left;color: orange;background: black;\"> AlienVault OTX Summary</h4></div> \n<table style=\"width: 506px; border-color: #ffffff;\" border=\"1\">\n<tbody>\n<tr>\n<td style=\"width: 45px;font-size:16px;font-weight: normal\"><strong>Tags</strong></td>\n<td> <div class=\"font-size-14 font-weight-normal\">{{(vars.steps.Get_Reputation_from_AlienVault_OTX.data.results | json_query(\"[*].tags[]\") | unique | string).replace(\"[\",\"\").replace(\"]\",\"\")}}</div></td>\n</tr>\n</tbody>\n</table>\n<p>{% endif %}</p>\n"
                },
                "version": "3.1.1",
                "connector": "cyops_utilities",
                "operation": "format_richtext",
                "ignore_errors": true,
                "operationTitle": "Utils: Format as RichText",
                "step_variables": []
              },
              "status": null,
              "top": "350",
              "left": "2725",
              "stepType": "/api/3/workflow_step_types/0109f35d-090b-4a2b-bd8a-94cbc3508562",
              "uuid": "2a86f387-914c-4c91-901a-3c7e2c7048f9"
            },
            {
              "@type": "WorkflowStep",
              "name": "Start",
              "description": "Indicator reputation is set as 'TBD' by 'Create and Link Indicator' utility playbook. We can ignore those indicators when triggering this PB",
              "arguments": {
                "resource": "indicators",
                "resources": [
                  "indicators"
                ],
                "step_variables": {
                  "input": {
                    "params": {
                      "indicator_value": "{{ vars.indicator_value }}"
                    },
                    "records": [
                      "{{vars.input.records[0]}}"
                    ]
                  }
                },
                "fieldbasedtrigger": {
                  "sort": [],
                  "limit": 30,
                  "logic": "AND",
                  "filters": [
                    {
                      "type": "object",
                      "field": "typeofindicator",
                      "value": "/api/3/picklists/5a5a7d42-be27-4903-858a-19909ebfa1eb",
                      "_value": {
                        "@id": "/api/3/picklists/5a5a7d42-be27-4903-858a-19909ebfa1eb",
                        "itemValue": "Domain"
                      },
                      "operator": "eq"
                    },
                    {
                      "type": "object",
                      "field": "indicatorStatus",
                      "value": "/api/3/picklists/4218cb58-4de5-4eff-ad08-185d36ef9bab",
                      "_value": {
                        "@id": "/api/3/picklists/4218cb58-4de5-4eff-ad08-185d36ef9bab",
                        "itemValue": "Whitelisted"
                      },
                      "operator": "neq"
                    },
                    {
                      "logic": "OR",
                      "filters": [
                        {
                          "type": "object",
                          "field": "reputation",
                          "value": "true",
                          "_value": {
                            "@id": "true",
                            "display": "",
                            "itemValue": ""
                          },
                          "operator": "isnull"
                        },
                        {
                          "type": "object",
                          "field": "reputation",
                          "value": "/api/3/picklists/ae98ebc6-beef-4882-9980-1d88fc6d87cd",
                          "_value": {
                            "@id": "/api/3/picklists/ae98ebc6-beef-4882-9980-1d88fc6d87cd",
                            "itemValue": "TBD"
                          },
                          "operator": "eq"
                        }
                      ]
                    }
                  ]
                }
              },
              "status": null,
              "top": "670",
              "left": "125",
              "stepType": "/api/3/workflow_step_types/ea155646-3821-4542-9702-b246da430a8d",
              "uuid": "30c8d3ed-3507-4392-ba43-dfa2bf4105d0"
            },
            {
              "@type": "WorkflowStep",
              "name": "Set Malicious",
              "description": null,
              "arguments": {
                "Reputation_Type_IRI": "{{(\"IndicatorReputation\" | picklist(\"Malicious\"))[\"@id\"]}}",
                "Reputation_Type_Text": "Malicious"
              },
              "status": null,
              "top": "350",
              "left": "3375",
              "stepType": "/api/3/workflow_step_types/04d0cf46-b6a8-42c4-8683-60a7eaa69e8f",
              "uuid": "3857ea71-e48f-42b9-a0ec-c4d8beafd8be"
            },
            {
              "@type": "WorkflowStep",
              "name": "Exit",
              "description": null,
              "arguments": {
                "params": [],
                "version": "3.2.1",
                "connector": "cyops_utilities",
                "operation": "no_op",
                "operationTitle": "Utils: No Operation",
                "step_variables": []
              },
              "status": null,
              "top": "750",
              "left": "775",
              "stepType": "/api/3/workflow_step_types/0109f35d-090b-4a2b-bd8a-94cbc3508562",
              "uuid": "3e633ed1-31d8-418b-9ec4-a0352826adaa"
            },
            {
              "@type": "WorkflowStep",
              "name": "Is Malicious",
              "description": null,
              "arguments": {
                "conditions": [
                  {
                    "option": "Malicious",
                    "step_iri": "/api/3/workflow_steps/3857ea71-e48f-42b9-a0ec-c4d8beafd8be",
                    "condition": "{{ vars.last_analysis_stats.malicious > 0 }}",
                    "step_name": "Set Malicious"
                  },
                  {
                    "option": "Safe",
                    "step_iri": "/api/3/workflow_steps/ebf3a072-ccd8-48ed-a243-c46ed7557968",
                    "condition": "{{ vars.last_analysis_stats.harmless > vars.last_analysis_stats.undetected }}",
                    "step_name": "Set Good"
                  },
                  {
                    "option": "No Reputation",
                    "default": true,
                    "step_iri": "/api/3/workflow_steps/b9a6103b-218e-4094-9aae-25a2d804ef5a",
                    "step_name": "Set No Reputation"
                  },
                  {
                    "option": "Suspicious",
                    "step_iri": "/api/3/workflow_steps/b4c5371b-375a-49e8-8efc-6fd4bb479de2",
                    "condition": "{{ vars.last_analysis_stats.suspicious > 0 }}",
                    "step_name": "Set Suspicious"
                  }
                ]
              },
              "status": null,
              "top": "500",
              "left": "3060",
              "stepType": "/api/3/workflow_step_types/12254cf5-5db7-4b1a-8cb1-3af081924b28",
              "uuid": "3e687780-5440-4b00-a419-c23279ad838e"
            },
            {
              "@type": "WorkflowStep",
              "name": "Compute VT Categories",
              "description": null,
              "arguments": {
                "when": "{{(vars.steps.Get_Domain_Reputation_from_VT.data.attributes.categories != None and vars.steps.Get_Domain_Reputation_from_VT.data.attributes.categories)}}",
                "params": {
                  "data": "{{vars.steps.Get_Domain_Reputation_from_VT.data.attributes.categories}}",
                  "styling": true,
                  "row_fields": "",
                  "table_style": "{ 'width':'auto','font':'10px;'}"
                },
                "version": "3.1.2",
                "connector": "cyops_utilities",
                "operation": "json_to_html",
                "operationTitle": "Utils: Convert JSON into a HTML Table",
                "step_variables": []
              },
              "status": null,
              "top": "990",
              "left": "2075",
              "stepType": "/api/3/workflow_step_types/0109f35d-090b-4a2b-bd8a-94cbc3508562",
              "uuid": "45c1d195-4d85-46d0-a458-a477d8b80bcb"
            },
            {
              "@type": "WorkflowStep",
              "name": "Whois Information from VT",
              "description": null,
              "arguments": {
                "when": "{{(vars.whoisdata_dict | length > 0)}}",
                "params": {
                  "data": "{{vars.whoisdata_dict}}",
                  "styling": true,
                  "row_fields": "",
                  "table_style": "{ 'width':'auto','font':'10px;'}"
                },
                "version": "3.1.2",
                "connector": "cyops_utilities",
                "operation": "json_to_html",
                "operationTitle": "Utils: Convert JSON into a HTML Table",
                "step_variables": []
              },
              "status": null,
              "top": "990",
              "left": "1425",
              "stepType": "/api/3/workflow_step_types/0109f35d-090b-4a2b-bd8a-94cbc3508562",
              "uuid": "4c3d889f-30ea-409e-99d5-d3cd17c8435f"
            },
            {
              "@type": "WorkflowStep",
              "name": "Compute IP Stack Summary",
              "description": null,
              "arguments": {
                "params": {
                  "value": "<p>{% if vars.foundIpStackReputation %}</p>\n<div class=\"font-size-11 ng-binding padding-bottom-sm\"><h4 style=\"background: #404142;padding: 5px;text-align: left;color: orange;background: black;\"> IP Stack</h4></div>\n<table>\n<tbody>\n<tr>\n<td style=\"vertical-align: top;\">\n<p><span style=\"font-size: 10pt;\"><strong>{% if vars.foundIpStackReputation%}</strong></span></p>\n<div class=\"font-size-17 margin-top-12 padding-bottom-sm padding-left-sm\"><strong>Location Summary:</strong></div> \n<table style=\"width: 506px;\" border=\"1\" >\n<tbody>\n<tr style=\"height: 16px;\">\n<td style=\"border: 1px solid white; text-align: left; width: 135px; height: 16px;\"><span style=\"font-size: 10pt;\">Country</span></td>\n<td style=\"border: 1px solid white; text-align: left; width: 370px; height: 16px;\"><span style=\"font-size: 10pt;\">{{vars.steps.Geo_Locate_Domain.data[0]['country_name']}}</span></td>\n</tr>\n<tr style=\"height: 16px;\">\n<td style=\"border: 1px solid white; text-align: left; width: 135px; height: 16px;\"><span style=\"font-size: 10pt;\">City</span></td>\n<td style=\"border: 1px solid white; text-align: left; width: 370px; height: 16px;\"><span style=\"font-size: 10pt;\">{{vars.steps.Geo_Locate_Domain.data[0].city}}</span></td>\n</tr>\n<tr style=\"height: 16.9034px;\">\n<td style=\"border: 1px solid white; text-align: left; width: 135px; height: 16px;\"><span style=\"font-size: 10pt;;\">Latitude</span></td>\n<td style=\"border: 1px solid white; text-align: left; width: 370px; height: 16px;\"><span style=\"font-size: 10pt;\">{{vars.steps.Geo_Locate_Domain.data[0].latitude}}</span></td>\n</tr>\n<tr style=\"height: 16.9034px;\">\n<td style=\"border: 1px solid white; text-align: left; width: 135px; height: 16px;\"><span style=\"font-size: 10pt;\">Longitude</span></td>\n<td style=\"border: 1px solid white; text-align: left; width: 370px; height: 16px;\"><span style=\"font-size: 10pt;\">{{vars.steps.Geo_Locate_Domain.data[0].longitude}}</span></td>\n</tr>\n</tbody>\n</table>\n<td>\n\n<div class=\"font-size-17  padding-bottom-sm\"><strong>Map Location </strong></div>\n<img src=\"https://maps.googleapis.com/maps/api/staticmap?key={{vars.googleMapAPIkey}}&center={{vars.steps.Geo_Locate_Domain.data[0].latitude}},{{vars.steps.Geo_Locate_Domain.data[0].longitude}}&zoom=13&format=png&maptype=roadmap&style=element:geometry|color:0x242f3e&style=element:labels.text.fill|color:0x746855&style=element:labels.text.stroke|color:0x242f3e&style=feature:administrative.locality|element:labels.text.fill|color:0xd59563&style=feature:poi|element:labels.text.fill|color:0xd59563&style=feature:poi.park|element:geometry|color:0x263c3f&style=feature:poi.park|element:labels.text.fill|color:0x6b9a76&style=feature:road|element:geometry|color:0x38414e&style=feature:road|element:geometry.stroke|color:0x212a37&style=feature:road|element:labels.text.fill|color:0x9ca5b3&style=feature:road.highway|element:geometry|color:0x746855&style=feature:road.highway|element:geometry.stroke|color:0x1f2835&style=feature:road.highway|element:labels.text.fill|color:0xf3d19c&style=feature:transit|element:geometry|color:0x2f3948&style=feature:transit.station|element:labels.text.fill|color:0xd59563&style=feature:water|element:geometry|color:0x17263c&style=feature:water|element:labels.text.fill|color:0x515c6d&style=feature:water|element:labels.text.stroke|color:0x17263c&size=600x300&markers=size:mid|color:0xff0000|label:|{{vars.steps.Geo_Locate_Domain.data[0].latitude}},{{vars.steps.Geo_Locate_Domain.data[0].longitude}}\" alt=\"\" width=\"500px\" height=\"300\" />\n{% endif %}\n</td>\n</tr>\n</tbody>\n</table>\n"
                },
                "version": "3.1.2",
                "connector": "cyops_utilities",
                "operation": "format_richtext",
                "ignore_errors": true,
                "operationTitle": "Utils: Format as RichText (Markdown)",
                "step_variables": []
              },
              "status": null,
              "top": "30",
              "left": "2725",
              "stepType": "/api/3/workflow_step_types/0109f35d-090b-4a2b-bd8a-94cbc3508562",
              "uuid": "57a5b835-5ffe-4701-8585-b9d7e3474e27"
            },
            {
              "@type": "WorkflowStep",
              "name": "Get Reputation from URLVoid",
              "description": null,
              "arguments": {
                "name": "URLVoid",
                "config": "80158417-6916-4f4f-b979-fc84ea02e2be",
                "params": {
                  "domain": "{{vars.indicator_value}}",
                  "rescan": true
                },
                "version": "1.1.0",
                "connector": "urlvoid",
                "operation": "domain_reputation",
                "ignore_errors": true,
                "operationTitle": "Get Website Reputation ",
                "step_variables": {
                  "foundDomainReputation": "{{ ( vars.result.data.results and vars.result.data.results | length > 0 ) | ternary(true,false) }}"
                }
              },
              "status": null,
              "top": "510",
              "left": "2400",
              "stepType": "/api/3/workflow_step_types/0bfed618-0316-11e7-93ae-92361f002671",
              "uuid": "64ce8347-7e04-4123-8ddc-890206980d22"
            },
            {
              "@type": "WorkflowStep",
              "name": "Compute DNS Records",
              "description": null,
              "arguments": {
                "when": "{{(vars.steps.Get_Domain_Reputation_from_VT.data.attributes['last_dns_records'] | length > 0)}}",
                "params": {
                  "data": "{{vars.steps.Get_Domain_Reputation_from_VT.data.attributes['last_dns_records']}}",
                  "styling": true,
                  "row_fields": "['type','value']",
                  "table_style": "{ 'width':'auto','font':'10px;'}"
                },
                "version": "3.1.2",
                "connector": "cyops_utilities",
                "operation": "json_to_html",
                "operationTitle": "Utils: Convert JSON into a HTML Table",
                "step_variables": []
              },
              "status": null,
              "top": "990",
              "left": "2400",
              "stepType": "/api/3/workflow_step_types/0109f35d-090b-4a2b-bd8a-94cbc3508562",
              "uuid": "6537480e-ce13-4822-a5a3-889ea162cded"
            },
            {
              "@type": "WorkflowStep",
              "name": "Geo Locate Domain",
              "description": null,
              "arguments": {
                "name": "IPStack",
                "config": "89a736ae-5c81-45d0-9ad3-8a4e7189f7c7",
                "params": {
                  "query": "{{vars.indicator_value}}",
                  "fields": "",
                  "enable_hostname": false,
                  "enable_security": false
                },
                "version": "1.0.0",
                "connector": "ipstack",
                "operation": "domain_locate",
                "ignore_errors": true,
                "operationTitle": "Geolocate Domain",
                "step_variables": {
                  "foundIpStackReputation": "{{ ( vars.result.data and (vars.result.data | length > 0) ) | ternary(true,false) }}"
                }
              },
              "status": null,
              "top": "30",
              "left": "2400",
              "stepType": "/api/3/workflow_step_types/0bfed618-0316-11e7-93ae-92361f002671",
              "uuid": "6c56c261-fd49-4949-9a7c-2a456643f7bf"
            },
            {
              "@type": "WorkflowStep",
              "name": "Is Referenced",
              "description": null,
              "arguments": {
                "conditions": [
                  {
                    "option": "Referenced",
                    "step_iri": "/api/3/workflow_steps/cabc1a8f-0460-425c-acc0-7685859b281b",
                    "condition": "{{ vars.input.params['indicator_value'] | length > 0 }}"
                  },
                  {
                    "option": "Upon Create",
                    "default": true,
                    "step_iri": "/api/3/workflow_steps/02b321a1-a785-4f50-8e6d-d43637daa27d"
                  }
                ]
              },
              "status": null,
              "top": "510",
              "left": "4025",
              "stepType": "/api/3/workflow_step_types/12254cf5-5db7-4b1a-8cb1-3af081924b28",
              "uuid": "a0d25daa-2ccf-4d83-87f1-5bed5f32dd41"
            },
            {
              "@type": "WorkflowStep",
              "name": "Enrichment Summary",
              "description": null,
              "arguments": {
                "params": {
                  "value": "{{vars.steps.Compute_VT_Summary.data['formatted_string']}} \n\n{{vars.steps.Compute_Fortinet_Web_Filter_Summary.data['formatted_string']}}\n\n{{vars.steps.Compute_Anomali_Summary.data['formatted_string']}}\n\n{{vars.steps.Compute_IP_Stack_Summary.data['formatted_string']}}\n\n{{vars.steps.Compute_AV_OTX_Summary.data['formatted_string']}}\n\n{{vars.steps.Compute_VT_Whois.data['formatted_string']}}\n\n{{vars.steps.Compute_URLVoid_Summary.data['formatted_string']}}  \n\n{{vars.steps.Compute_MxToolbox_Summary.data['formatted_string']}}\n\n\n\n "
                },
                "version": "3.1.2",
                "connector": "cyops_utilities",
                "operation": "format_richtext",
                "operationTitle": "Utils: Format as RichText",
                "step_variables": []
              },
              "status": null,
              "top": "510",
              "left": "3700",
              "stepType": "/api/3/workflow_step_types/0109f35d-090b-4a2b-bd8a-94cbc3508562",
              "uuid": "a591897f-1d42-4f30-be25-e1900a5e7ba5"
            },
            {
              "@type": "WorkflowStep",
              "name": "Compute VT Whois",
              "description": null,
              "arguments": {
                "config": "2b518f8c-a08a-4216-9524-6af1c9173b03",
                "params": {
                  "value": "<div class=\"font-size-11 ng-binding padding-bottom-sm\"><h4 style=\"background: #404142;padding: 5px;text-align: left;color: orange;background: black;\"> Additional Information</h4></div>\n\n<div style=\"white-space:nowrap;width:auto;display: flex;gap:20px;\">\n\n{% if (vars.whoisdata_dict | length > 0)%}\n<div><div class=\"font-size-17 padding-left-sm padding-bottom-sm\"><strong>Whois Lookup</strong></div>\n{{vars.steps.Whois_Information_from_VT.data}}\n</div>{%endif%}\n{%if (vars.steps.Get_Domain_Reputation_from_VT.data.attributes['last_dns_records'] | length > 0) %}\n<div><div class=\"font-size-17 padding-left-sm padding-bottom-sm\"><strong>DNS Records</strong></div>\n{{vars.steps.Compute_DNS_Records.data}}\n</div>\n{%endif%}\n{% if  vars.steps.Compute_VT_Categories.data %}\n<div><div class=\"font-size-17 padding-left-sm padding-bottom-sm\"><strong>Security Vendor Scanning Results</strong></div>\n{{vars.steps.Compute_VT_Categories.data}}\n</div>\n {%endif%}\n</div>"
                },
                "version": "3.1.2",
                "connector": "cyops_utilities",
                "operation": "format_richtext",
                "operationTitle": "Utils: Format as RichText",
                "step_variables": []
              },
              "status": null,
              "top": "990",
              "left": "2725",
              "stepType": "/api/3/workflow_step_types/0109f35d-090b-4a2b-bd8a-94cbc3508562",
              "uuid": "ac8bc8d0-6607-460b-ab63-aa2e947bc8ef"
            },
            {
              "@type": "WorkflowStep",
              "name": "Set Suspicious",
              "description": null,
              "arguments": {
                "Reputation_Type_IRI": "{{(\"IndicatorReputation\" | picklist(\"Suspicious\"))[\"@id\"]}}",
                "Reputation_Type_Text": "Suspicious"
              },
              "status": null,
              "top": "830",
              "left": "3375",
              "stepType": "/api/3/workflow_step_types/04d0cf46-b6a8-42c4-8683-60a7eaa69e8f",
              "uuid": "b4c5371b-375a-49e8-8efc-6fd4bb479de2"
            },
            {
              "@type": "WorkflowStep",
              "name": "Set No Reputation",
              "description": null,
              "arguments": {
                "Reputation_Type_IRI": "{{(\"IndicatorReputation\" | picklist(\"No Reputation Available\"))[\"@id\"]}}",
                "Reputation_Type_Text": "No Reputation Available"
              },
              "status": null,
              "top": "670",
              "left": "3375",
              "stepType": "/api/3/workflow_step_types/04d0cf46-b6a8-42c4-8683-60a7eaa69e8f",
              "uuid": "b9a6103b-218e-4094-9aae-25a2d804ef5a"
            },
            {
              "@type": "WorkflowStep",
              "name": "Compute MxToolbox Summary",
              "description": null,
              "arguments": {
                "params": {
                  "value": "<p>{% if vars.foundDomainMxReputation %}</p>\n<div class=\"card-container-body\" style=\"width: 200px;\">\n<div class=\"card-number \" style=\"font-size: 50px; font-weight: normal;\"><span class=\"card-count\">{{vars.steps.Get_Domain_Reputation_from_MxToolbox.data.result.MxRep}}</span>\n<div class=\"font-size-12 ng-binding\">{% if vars.steps.Get_Domain_Reputation_from_MxToolbox.data.result.MxRep == 100 %}Not Blacklisted {%else%}Blacklisted {%endif%}</div>\n<div class=\"font-size-14 ng-binding\"><strong>MxToolbox</strong></div>\n</div>\n</div>\n<p>{% endif %}</p>\n"
                },
                "version": "3.0.3",
                "connector": "cyops_utilities",
                "operation": "format_richtext",
                "ignore_errors": true,
                "operationTitle": "Utils: Format as RichText",
                "step_variables": []
              },
              "status": null,
              "top": "670",
              "left": "2725",
              "stepType": "/api/3/workflow_step_types/0109f35d-090b-4a2b-bd8a-94cbc3508562",
              "uuid": "c1e368b1-ad55-4820-8f77-ea7992edb190"
            },
            {
              "@type": "WorkflowStep",
              "name": "Configuration",
              "description": null,
              "arguments": {
                "whoisdata_dict": "{}",
                "categories_dict": "{}",
                "googleMapAPIkey": "AIzaSyDy4tlleelMlMRB-HuBbgxeBMrfUJQF2ZE",
                "indicator_value": "{{vars.input.params['indicator_value'] | ternary(vars.input.params['indicator_value'],vars.input.records[0].value) }}",
                "foundAnomaliReputation": "false",
                "foundIpStackReputation": "false",
                "VT_reputation_threshold": "5",
                "foundDomainMxReputation": "false"
              },
              "status": null,
              "top": "590",
              "left": "775",
              "stepType": "/api/3/workflow_step_types/04d0cf46-b6a8-42c4-8683-60a7eaa69e8f",
              "uuid": "c2e6cb54-8213-4f30-a6fc-b53712ad94e5"
            },
            {
              "@type": "WorkflowStep",
              "name": "Compute VT Summary",
              "description": null,
              "arguments": {
                "config": "2b518f8c-a08a-4216-9524-6af1c9173b03",
                "params": {
                  "value": "<div class=\"font-size-11 ng-binding padding-bottom-sm\"><h4 style=\"background: #404142;padding: 5px;text-align: left;color: orange;background: black;\"> VirusTotal Detection Summary</h4></div>\n<table style=\"border-color: #04080c;\" border=\"1\" class=\"font-normal\">\n<tr><td style=\"border-color: #04080c;\">\n<table style=\"color:white;font-size:11;\" class=\"no-border\">\n<tr>\n<td>\n<html>\n  <head>\n    <title>Title of the document</title>\n    <style>\n      span.circle {\n        background: #2f3f51;\n        border-radius: 50%;\n        -moz-border-radius: 50%;\n        -webkit-border-radius: 50%;\n        display: inline-block;\n         font-weight: bold;\n        line-height: 100px;\n        margin-right: 5px;\n        text-align: center;\n        width: 100px;\n      font-size:15px;\n     border-color: Black;\n      }\n    </style>\n  </head>\n  <body><span class=\"circle\"><i style=\"font-size:25px;color:red \">\n   {{vars.last_analysis_stats.malicious}}</i>/{{vars.last_analysis_stats.values() | list | sum}}</span>\n  </body>\n</html>\n</td>\n\n<td>\n<div class=\"font-size-14 ng-binding\">Malicious</div>\n<div class=\"card-container-body\" style=\"width: 100px;font-size:46px;\">\n<div class=\"card-number\"; style=\"font-size:45px;  border-left: 5px solid red;background:#141b23\">{{vars.last_analysis_stats.malicious}}</div>\n</div>\n</td>\n<td>\n<div class=\"font-size-14 ng-binding\">Suspicious</div>\n<div class=\"card-container-body\" style=\"width: 100px;\">\n<div class=\"card-number\" style=\"font-size:45px;  border-left: 5px solid orange; background:#141b23\">{{vars.last_analysis_stats.suspicious}}</div>\n</div>\n</td>\n<td>\n<div class=\"font-size-14 ng-binding\">Harmless</div>\n<div class=\"card-container-body\" style=\"width: 100px;\">\n<div class=\"card-number\" style=\"font-size:45px;  border-left: 5px solid green; background:#141b23\">{{vars.last_analysis_stats.harmless}}</div></div>\n</td>\n</tr>\n</table>\n\n<td style=\"vertical-align:top; border-color: #04080c;\">\n<table style=\"background-color: #1b2430; color:white;font-size:16;\" class=\"margin-10 no-border\">\n<tr>\n<div class=\"margin-top-md\">\n<i class=\"fa fa-group margin-left-md margin-right-sm\"></i> Community Votes</div>\n\n<td style=\"width: 100px;text-align: center;background:#141b23\">\n<i class=\"\tfa fa-thumbs-o-up\" style=\"font-size:25px;color:green\"></i>\n<div class=\"font-size-11 ng-binding\">Harmless {{vars.community_votes.harmless}}</div>\n</td>\n<td style=\"width: 100px;text-align: center;background:#141b23\">\n<i class=\"fa fa-thumbs-o-down\" style=\"font-size:25px;color:red \"></i>\n<div class=\"font-size-11 ng-binding\">Malicious {{vars.community_votes.malicious}}</div>\n</td>\n</tr>\n</table>\n</div>\n</td>\n</tr>\n</table>\n\n       \n\n"
                },
                "version": "3.1.1",
                "connector": "cyops_utilities",
                "operation": "format_richtext",
                "operationTitle": "Utils: Format as RichText",
                "step_variables": []
              },
              "status": null,
              "top": "990",
              "left": "1750",
              "stepType": "/api/3/workflow_step_types/0109f35d-090b-4a2b-bd8a-94cbc3508562",
              "uuid": "c52c8729-337c-424d-bfca-af3b4ed9cad1"
            },
            {
              "@type": "WorkflowStep",
              "name": "Summary",
              "description": null,
              "arguments": {
                "reputation": "{{vars.Reputation_Type_Text}}",
                "reputation_iri": "{{vars.Reputation_Type_IRI}}",
                "enrichment_summary": "{{vars.steps.Enrichment_Summary.data['formatted_string']}}"
              },
              "status": null,
              "top": "590",
              "left": "4350",
              "stepType": "/api/3/workflow_step_types/04d0cf46-b6a8-42c4-8683-60a7eaa69e8f",
              "uuid": "cabc1a8f-0460-425c-acc0-7685859b281b"
            },
            {
              "@type": "WorkflowStep",
              "name": "Compute Fortinet Web Filter Summary",
              "description": null,
              "arguments": {
                "params": {
                  "value": "<p>{% if  vars.foundFortinetWebFilterReputation %}</p>\n\n<div class=\"font-size-11 ng-binding padding-bottom-sm\"><h4 style=\"background: #404142;padding: 5px;text-align: left;color: orange;background: black;\"> FortiGuard Lookup</h4></div>\n<table style=\"width: 506px; border-color: #ffffff;\" border=\"1\">\n<tbody>\n<tr><td><div class=\"font-size-14 font-weight-normal\">Category</div></td>\n<td ><div class=\"font-size-14 font-weight-normal\">{{vars.steps.Get_Domain_Reputation_from_Fortinet_Web_Filter.data.category}}</div></td></tr>\n</tbody>\n</table>\n<p>{% endif %}</p>\n"
                },
                "version": "3.1.1",
                "connector": "cyops_utilities",
                "operation": "format_richtext",
                "ignore_errors": true,
                "operationTitle": "Utils: Format as RichText",
                "step_variables": []
              },
              "status": null,
              "top": "830",
              "left": "2725",
              "stepType": "/api/3/workflow_step_types/0109f35d-090b-4a2b-bd8a-94cbc3508562",
              "uuid": "ccb55494-0993-41c1-87e2-8716201f1e47"
            },
            {
              "@type": "WorkflowStep",
              "name": "Get Domain Reputation from MxToolbox",
              "description": null,
              "arguments": {
                "name": "MxToolbox",
                "config": "aa41f424-4472-4f04-aeec-0a17d6df45f8",
                "params": {
                  "value": "{{vars.indicator_value}}",
                  "object": "blacklist",
                  "api_method": "Lookup"
                },
                "version": "1.0.0",
                "connector": "mxtoolbox",
                "operation": "api_call",
                "ignore_errors": true,
                "operationTitle": "Get MxToolbox Records",
                "step_variables": {
                  "foundDomainMxReputation": "{{ ( vars.result.data and (vars.result.data | length > 0) ) | ternary(true,false) }}"
                }
              },
              "status": null,
              "top": "670",
              "left": "2400",
              "stepType": "/api/3/workflow_step_types/0bfed618-0316-11e7-93ae-92361f002671",
              "uuid": "d0bae75f-5a3b-45a3-956c-6dd79b98e53a"
            },
            {
              "@type": "WorkflowStep",
              "name": "Get Domain Reputation from Fortinet Web Filter",
              "description": null,
              "arguments": {
                "name": "Fortinet Web Filter Lookup",
                "config": "30ec97b3-5d84-4372-9f13-f085f0208444",
                "params": {
                  "sample_url": "{{vars.indicator_value}}"
                },
                "version": "1.0.0",
                "connector": "fortinet-web-filter-lookup",
                "operation": "url_review",
                "ignore_errors": true,
                "operationTitle": "Check Category of Domain or URL",
                "step_variables": {
                  "foundFortinetWebFilterReputation": "{{ ( vars.result.data and (vars.result.data | length > 0) ) | ternary(true,false) }}"
                }
              },
              "status": null,
              "top": "830",
              "left": "2400",
              "stepType": "/api/3/workflow_step_types/0bfed618-0316-11e7-93ae-92361f002671",
              "uuid": "d2b49e99-afbc-42e6-ba09-c4c2aa3cfd71"
            },
            {
              "@type": "WorkflowStep",
              "name": "Compute Anomali Summary",
              "description": null,
              "arguments": {
                "params": {
                  "value": "<p>{% if vars.foundAnomaliReputation %}</p>\n<div class=\"font-size-11 ng-binding padding-bottom-sm\"><h4 style=\"background: #404142;padding: 5px;text-align: left;color: orange;background: black;\"> Anomali Threatstream Detection Summary</h4></div>\n<div class=\"card-container-body\" style=\"width: 150px;\">\n{%if vars.steps.Get_Domain_Reputation_from_Anomali.data.objects[0].threatscore !=0 %}\n<div class=\"card-number padding-top-sm padding-bottom-sm\" style=\" border-left: 5px solid red;background:#141b23\">\n <div class=\"line-height-1\"><a href=\"https://ui.threatstream.com/detail/domain/{{vars.indicator_value}}\" target=\"_blank\" rel=\"noopener noreferrer\" class=\"font-size-8em\"> <span class=\"card-count\">{{vars.steps.Get_Domain_Reputation_from_Anomali.data.objects[0].threatscore}} </span> </a>\n<div class=\"font-size-14 font-weight-normall padding-top-sm padding-bottom-sm\">Severity: {{vars.steps.Get_Domain_Reputation_from_Anomali.data.objects[0].meta.severity}}</div>\n{%else%}\n<div class=\"card-number padding-top-sm padding-bottom-sm\" style=\" border-left: 5px solid red\">\n <div class=\"line-height-1\"><a href=\"https://ui.threatstream.com/detail/domain/{{vars.indicator_value}}\" target=\"_blank\" rel=\"noopener noreferrer\" class=\"font-size-8em\"> <span class=\"card-count\">{{vars.steps.Get_Domain_Reputation_from_Anomali.data.objects[0].threatscore}} </span> </a>\n<div class=\"font-size-14 font-weight-normall padding-top-sm padding-bottom-sm\">Severity: {{vars.steps.Get_Domain_Reputation_from_Anomali.data.objects[0].meta.severity}}{% endif %}\n</div>\n</div>\n</div>\n<p>{% endif %}</p>\n"
                },
                "version": "3.1.2",
                "connector": "cyops_utilities",
                "operation": "format_richtext",
                "ignore_errors": true,
                "operationTitle": "Utils: Format as RichText",
                "step_variables": []
              },
              "status": null,
              "top": "190",
              "left": "2725",
              "stepType": "/api/3/workflow_step_types/0109f35d-090b-4a2b-bd8a-94cbc3508562",
              "uuid": "d4f40f92-4761-416c-9fe9-741116b8b719"
            },
            {
              "@type": "WorkflowStep",
              "name": "Get Domain Reputation from Anomali",
              "description": null,
              "arguments": {
                "name": "Anomali ThreatStream",
                "config": "8827ae00-b86a-4ed4-aa2c-deae42b1d993",
                "params": {
                  "value": "{{vars.indicator_value}}",
                  "validation": false,
                  "filter_option": "Exact",
                  "record_number": "Fetch All Records"
                },
                "version": "2.0.0",
                "connector": "threatstream",
                "operation": "domain_reputation",
                "ignore_errors": true,
                "operationTitle": "Get Domain Reputation",
                "step_variables": {
                  "foundAnomaliReputation": "{{ ( vars.result.data.objects and vars.result.data.objects | length > 0 ) | ternary(true,false) }}"
                }
              },
              "status": null,
              "top": "190",
              "left": "2400",
              "stepType": "/api/3/workflow_step_types/0bfed618-0316-11e7-93ae-92361f002671",
              "uuid": "d5f8629f-6dc8-4f29-a1b7-81663d1e1a51"
            },
            {
              "@type": "WorkflowStep",
              "name": "Compute URLVoid Summary",
              "description": null,
              "arguments": {
                "params": {
                  "value": "<p>{% if vars.foundDomainReputation %}</p>\n<div class=\"card-container-body\" style=\"width: 200px;\">\n<div class=\"card-number\"><a href=\"https://www.urlvoid.com/scan/{{vars.record.value}}\" target=\"&quot;_blank&quot;&quot;\"> <span class=\"card-count\">{%if 'detections' in vars.steps.Get_Reputation_from_URLVoid.data %} {{vars.steps.Get_Reputation_from_URLVoid.data.detections.count}}{%else%} 0 {%endif%}</span> </a>\n<div class=\"font-size-12 ng-binding\">IP Address: {{vars.steps.Get_Reputation_from_URLVoid.data.details.ip.addr}}</div>\n<div class=\"font-size-14 ng-binding\"><strong>URLVoid</strong></div>\n</div>\n</div>\n<p>{% endif %}</p>\n"
                },
                "version": "3.0.3",
                "connector": "cyops_utilities",
                "operation": "format_richtext",
                "ignore_errors": true,
                "operationTitle": "Utils: Format as RichText",
                "step_variables": []
              },
              "status": null,
              "top": "510",
              "left": "2725",
              "stepType": "/api/3/workflow_step_types/0109f35d-090b-4a2b-bd8a-94cbc3508562",
              "uuid": "e78bce1a-36e7-4311-89f8-cf2ec90e025b"
            },
            {
              "@type": "WorkflowStep",
              "name": "Set Good",
              "description": null,
              "arguments": {
                "Reputation_Type_IRI": "{{(\"IndicatorReputation\" | picklist(\"Good\"))[\"@id\"]}}",
                "Reputation_Type_Text": "Good"
              },
              "status": null,
              "top": "510",
              "left": "3375",
              "stepType": "/api/3/workflow_step_types/04d0cf46-b6a8-42c4-8683-60a7eaa69e8f",
              "uuid": "ebf3a072-ccd8-48ed-a243-c46ed7557968"
            }
          ],
          "routes": [
            {
              "@type": "WorkflowRoute",
              "name": "Geo Locate Domain -> Compute IP Stack Summary",
              "targetStep": "/api/3/workflow_steps/57a5b835-5ffe-4701-8585-b9d7e3474e27",
              "sourceStep": "/api/3/workflow_steps/6c56c261-fd49-4949-9a7c-2a456643f7bf",
              "label": null,
              "isExecuted": false,
              "uuid": "06f3ba52-1795-4d7c-bc4a-c01095608e2d"
            },
            {
              "@type": "WorkflowRoute",
              "name": "Configuration -> Get Reputation from URLVoid",
              "targetStep": "/api/3/workflow_steps/64ce8347-7e04-4123-8ddc-890206980d22",
              "sourceStep": "/api/3/workflow_steps/c2e6cb54-8213-4f30-a6fc-b53712ad94e5",
              "label": null,
              "isExecuted": false,
              "uuid": "07f480bb-bcef-4259-929b-ab2bf802720e"
            },
            {
              "@type": "WorkflowRoute",
              "name": "Configuration -> Geo Locate Domain",
              "targetStep": "/api/3/workflow_steps/6c56c261-fd49-4949-9a7c-2a456643f7bf",
              "sourceStep": "/api/3/workflow_steps/c2e6cb54-8213-4f30-a6fc-b53712ad94e5",
              "label": null,
              "isExecuted": false,
              "uuid": "0bf9a0c2-8ce5-4345-9509-a96d2d889e3e"
            },
            {
              "@type": "WorkflowRoute",
              "name": "Get File Reputation from Anomali -> Compute Anomali Summary",
              "targetStep": "/api/3/workflow_steps/d4f40f92-4761-416c-9fe9-741116b8b719",
              "sourceStep": "/api/3/workflow_steps/d5f8629f-6dc8-4f29-a1b7-81663d1e1a51",
              "label": null,
              "isExecuted": false,
              "uuid": "0d546423-3987-40b0-8bfa-7cf55e78096a"
            },
            {
              "@type": "WorkflowRoute",
              "name": "Is Upon Create -> Update Record",
              "targetStep": "/api/3/workflow_steps/02b321a1-a785-4f50-8e6d-d43637daa27d",
              "sourceStep": "/api/3/workflow_steps/a0d25daa-2ccf-4d83-87f1-5bed5f32dd41",
              "label": "Upon Create",
              "isExecuted": false,
              "uuid": "0f44bebb-a7c9-4ee1-a810-736e8563f84d"
            },
            {
              "@type": "WorkflowRoute",
              "name": "Configuration -> Get Domain Reputation",
              "targetStep": "/api/3/workflow_steps/295a0467-b576-44c0-8cc8-5e812ed3c7d6",
              "sourceStep": "/api/3/workflow_steps/c2e6cb54-8213-4f30-a6fc-b53712ad94e5",
              "label": null,
              "isExecuted": false,
              "uuid": "2d3a8e98-ca14-4309-a6e3-7f62e3067e1a"
            },
            {
              "@type": "WorkflowRoute",
              "name": "Set No Reputation -> Enrichment Summary",
              "targetStep": "/api/3/workflow_steps/a591897f-1d42-4f30-be25-e1900a5e7ba5",
              "sourceStep": "/api/3/workflow_steps/b9a6103b-218e-4094-9aae-25a2d804ef5a",
              "label": null,
              "isExecuted": false,
              "uuid": "2fc3a1ec-beae-4575-a5b6-aeab3e2fce41"
            },
            {
              "@type": "WorkflowRoute",
              "name": "Set Good -> Enrichment Summary",
              "targetStep": "/api/3/workflow_steps/a591897f-1d42-4f30-be25-e1900a5e7ba5",
              "sourceStep": "/api/3/workflow_steps/ebf3a072-ccd8-48ed-a243-c46ed7557968",
              "label": null,
              "isExecuted": false,
              "uuid": "3924832b-8804-453e-8ded-57b29396f0c6"
            },
            {
              "@type": "WorkflowRoute",
              "name": "Compute URLVoid Summary -> Is Malicious",
              "targetStep": "/api/3/workflow_steps/3e687780-5440-4b00-a419-c23279ad838e",
              "sourceStep": "/api/3/workflow_steps/e78bce1a-36e7-4311-89f8-cf2ec90e025b",
              "label": null,
              "isExecuted": false,
              "uuid": "4df88ce6-ff2f-4e91-9a35-ccba70b74693"
            },
            {
              "@type": "WorkflowRoute",
              "name": "Is Malicious -> Set No Reputation",
              "targetStep": "/api/3/workflow_steps/b9a6103b-218e-4094-9aae-25a2d804ef5a",
              "sourceStep": "/api/3/workflow_steps/3e687780-5440-4b00-a419-c23279ad838e",
              "label": "No Reputation",
              "isExecuted": false,
              "uuid": "505e0657-d44c-43c6-9ff6-ffa14c23bc5c"
            },
            {
              "@type": "WorkflowRoute",
              "name": "Configuration -> Get Domain Reputation from MxToolbox",
              "targetStep": "/api/3/workflow_steps/d0bae75f-5a3b-45a3-956c-6dd79b98e53a",
              "sourceStep": "/api/3/workflow_steps/c2e6cb54-8213-4f30-a6fc-b53712ad94e5",
              "label": null,
              "isExecuted": false,
              "uuid": "55f32576-b1bd-4d4c-aa38-426f2fb75eb4"
            },
            {
              "@type": "WorkflowRoute",
              "name": "Compute VT Categories -> Compute DNS Records",
              "targetStep": "/api/3/workflow_steps/6537480e-ce13-4822-a5a3-889ea162cded",
              "sourceStep": "/api/3/workflow_steps/45c1d195-4d85-46d0-a458-a477d8b80bcb",
              "label": null,
              "isExecuted": false,
              "uuid": "5d65d25d-fbd0-4557-8540-ad490bbfed98"
            },
            {
              "@type": "WorkflowRoute",
              "name": "Has Dedicated Tenant Record -> Exit",
              "targetStep": "/api/3/workflow_steps/3e633ed1-31d8-418b-9ec4-a0352826adaa",
              "sourceStep": "/api/3/workflow_steps/235eaa62-6990-40bb-ab83-8d0cea217942",
              "label": "Yes, Enrich at Tenant Node",
              "isExecuted": false,
              "uuid": "61176e5f-8eb9-43a5-bb8d-c14791b0a0ab"
            },
            {
              "@type": "WorkflowRoute",
              "name": "Compute Fortinet Web Filter Summary -> Is Malicious",
              "targetStep": "/api/3/workflow_steps/3e687780-5440-4b00-a419-c23279ad838e",
              "sourceStep": "/api/3/workflow_steps/ccb55494-0993-41c1-87e2-8716201f1e47",
              "label": null,
              "isExecuted": false,
              "uuid": "66ef0eda-293e-424c-bf08-bca95a4a37c8"
            },
            {
              "@type": "WorkflowRoute",
              "name": "Compute MxToolbox Summary -> Is Malicious",
              "targetStep": "/api/3/workflow_steps/3e687780-5440-4b00-a419-c23279ad838e",
              "sourceStep": "/api/3/workflow_steps/c1e368b1-ad55-4820-8f77-ea7992edb190",
              "label": null,
              "isExecuted": false,
              "uuid": "71e38590-ab15-49d5-af12-8912b92bc41b"
            },
            {
              "@type": "WorkflowRoute",
              "name": "Compute DNS Records -> Compute VT Whois",
              "targetStep": "/api/3/workflow_steps/ac8bc8d0-6607-460b-ab63-aa2e947bc8ef",
              "sourceStep": "/api/3/workflow_steps/6537480e-ce13-4822-a5a3-889ea162cded",
              "label": null,
              "isExecuted": false,
              "uuid": "84f37a13-6082-4abb-b3a2-6fd2a9aced3d"
            },
            {
              "@type": "WorkflowRoute",
              "name": "Set Malicious -> Enrichment Summary",
              "targetStep": "/api/3/workflow_steps/a591897f-1d42-4f30-be25-e1900a5e7ba5",
              "sourceStep": "/api/3/workflow_steps/3857ea71-e48f-42b9-a0ec-c4d8beafd8be",
              "label": null,
              "isExecuted": false,
              "uuid": "859c6c4a-1fdc-4741-990a-c566edfe8051"
            },
            {
              "@type": "WorkflowRoute",
              "name": "Start -> Has Dedicated Tenant Record",
              "targetStep": "/api/3/workflow_steps/235eaa62-6990-40bb-ab83-8d0cea217942",
              "sourceStep": "/api/3/workflow_steps/30c8d3ed-3507-4392-ba43-dfa2bf4105d0",
              "label": null,
              "isExecuted": false,
              "uuid": "884ac6a8-0e26-4e04-b4da-49964dec06b5"
            },
            {
              "@type": "WorkflowRoute",
              "name": "Compute VT Summary -> categories",
              "targetStep": "/api/3/workflow_steps/45c1d195-4d85-46d0-a458-a477d8b80bcb",
              "sourceStep": "/api/3/workflow_steps/c52c8729-337c-424d-bfca-af3b4ed9cad1",
              "label": null,
              "isExecuted": false,
              "uuid": "8c831764-24d6-43cd-970c-88857e9a7d77"
            },
            {
              "@type": "WorkflowRoute",
              "name": "Get Reputation from AlienVault OTX -> Copy  of Compute IP Stack Summary",
              "targetStep": "/api/3/workflow_steps/2a86f387-914c-4c91-901a-3c7e2c7048f9",
              "sourceStep": "/api/3/workflow_steps/1afaa2be-453f-4b6d-8fb3-d574339d8580",
              "label": null,
              "isExecuted": false,
              "uuid": "94586e32-0598-4e2b-9904-6874f4f7b6a5"
            },
            {
              "@type": "WorkflowRoute",
              "name": "Enrichment Summary -> Is Upon Create",
              "targetStep": "/api/3/workflow_steps/a0d25daa-2ccf-4d83-87f1-5bed5f32dd41",
              "sourceStep": "/api/3/workflow_steps/a591897f-1d42-4f30-be25-e1900a5e7ba5",
              "label": null,
              "isExecuted": false,
              "uuid": "947837a0-a79b-4832-a59b-f6200423e53a"
            },
            {
              "@type": "WorkflowRoute",
              "name": "Compute IP Stack Summary -> Is Malicious",
              "targetStep": "/api/3/workflow_steps/3e687780-5440-4b00-a419-c23279ad838e",
              "sourceStep": "/api/3/workflow_steps/57a5b835-5ffe-4701-8585-b9d7e3474e27",
              "label": null,
              "isExecuted": false,
              "uuid": "94ad33e9-4d48-4082-a41c-9039cfdfba53"
            },
            {
              "@type": "WorkflowRoute",
              "name": "Is Malicious -> Set Malicious",
              "targetStep": "/api/3/workflow_steps/3857ea71-e48f-42b9-a0ec-c4d8beafd8be",
              "sourceStep": "/api/3/workflow_steps/3e687780-5440-4b00-a419-c23279ad838e",
              "label": "Malicious",
              "isExecuted": false,
              "uuid": "952abd20-2f10-4d64-bf9c-9d7bd5d151f4"
            },
            {
              "@type": "WorkflowRoute",
              "name": "Is Malicious -> Set Suspicious",
              "targetStep": "/api/3/workflow_steps/b4c5371b-375a-49e8-8efc-6fd4bb479de2",
              "sourceStep": "/api/3/workflow_steps/3e687780-5440-4b00-a419-c23279ad838e",
              "label": "Suspicious",
              "isExecuted": false,
              "uuid": "96fa2cc3-fe02-485d-82e1-b11fdfb0fe2d"
            },
            {
              "@type": "WorkflowRoute",
              "name": "Configuration -> Get Domain Reputation from Fortinet Web Filter",
              "targetStep": "/api/3/workflow_steps/d2b49e99-afbc-42e6-ba09-c4c2aa3cfd71",
              "sourceStep": "/api/3/workflow_steps/c2e6cb54-8213-4f30-a6fc-b53712ad94e5",
              "label": null,
              "isExecuted": false,
              "uuid": "994c3ec8-4eec-4be0-adb0-9b5e87ef0f7d"
            },
            {
              "@type": "WorkflowRoute",
              "name": "Set Suspicious -> Enrichment Summary",
              "targetStep": "/api/3/workflow_steps/a591897f-1d42-4f30-be25-e1900a5e7ba5",
              "sourceStep": "/api/3/workflow_steps/b4c5371b-375a-49e8-8efc-6fd4bb479de2",
              "label": null,
              "isExecuted": false,
              "uuid": "a2067163-2505-4cdc-8ccb-3219fb0418bb"
            },
            {
              "@type": "WorkflowRoute",
              "name": "Get Domain Reputation from VT -> Whois Information",
              "targetStep": "/api/3/workflow_steps/4c3d889f-30ea-409e-99d5-d3cd17c8435f",
              "sourceStep": "/api/3/workflow_steps/295a0467-b576-44c0-8cc8-5e812ed3c7d6",
              "label": null,
              "isExecuted": false,
              "uuid": "b3f39fbb-9774-453f-a793-2670f91970b3"
            },
            {
              "@type": "WorkflowRoute",
              "name": "Whois Information -> Compute VT Summary",
              "targetStep": "/api/3/workflow_steps/c52c8729-337c-424d-bfca-af3b4ed9cad1",
              "sourceStep": "/api/3/workflow_steps/4c3d889f-30ea-409e-99d5-d3cd17c8435f",
              "label": null,
              "isExecuted": false,
              "uuid": "b5c26f98-5eff-4484-be45-b6c34e9a6360"
            },
            {
              "@type": "WorkflowRoute",
              "name": "Is Malicious -> Set Good",
              "targetStep": "/api/3/workflow_steps/ebf3a072-ccd8-48ed-a243-c46ed7557968",
              "sourceStep": "/api/3/workflow_steps/3e687780-5440-4b00-a419-c23279ad838e",
              "label": "Safe",
              "isExecuted": false,
              "uuid": "b7b76079-251e-4537-ac57-a3f8e66e34bc"
            },
            {
              "@type": "WorkflowRoute",
              "name": "Is Upon Create -> Summary",
              "targetStep": "/api/3/workflow_steps/cabc1a8f-0460-425c-acc0-7685859b281b",
              "sourceStep": "/api/3/workflow_steps/a0d25daa-2ccf-4d83-87f1-5bed5f32dd41",
              "label": "Referenced",
              "isExecuted": false,
              "uuid": "b81954bc-2472-4794-85c1-7a8b216ab40f"
            },
            {
              "@type": "WorkflowRoute",
              "name": "Get Reputation from URLVoid -> Compute URLVoid Summary",
              "targetStep": "/api/3/workflow_steps/e78bce1a-36e7-4311-89f8-cf2ec90e025b",
              "sourceStep": "/api/3/workflow_steps/64ce8347-7e04-4123-8ddc-890206980d22",
              "label": null,
              "isExecuted": false,
              "uuid": "c5c4e831-f618-4e74-8bf3-e783979d7f3c"
            },
            {
              "@type": "WorkflowRoute",
              "name": "Has Dedicated Tenant Record -> Configuration",
              "targetStep": "/api/3/workflow_steps/c2e6cb54-8213-4f30-a6fc-b53712ad94e5",
              "sourceStep": "/api/3/workflow_steps/235eaa62-6990-40bb-ab83-8d0cea217942",
              "label": "No, Enrich Here",
              "isExecuted": false,
              "uuid": "c8ef21c7-14ff-45f8-b535-b1840dff15fb"
            },
            {
              "@type": "WorkflowRoute",
              "name": "Configuration -> Get Reputation from AlienVault OTX",
              "targetStep": "/api/3/workflow_steps/1afaa2be-453f-4b6d-8fb3-d574339d8580",
              "sourceStep": "/api/3/workflow_steps/c2e6cb54-8213-4f30-a6fc-b53712ad94e5",
              "label": null,
              "isExecuted": false,
              "uuid": "d32887e5-3c86-4cd6-ad62-d00524412d41"
            },
            {
              "@type": "WorkflowRoute",
              "name": "Configuration -> Get File Reputation from Anomali",
              "targetStep": "/api/3/workflow_steps/d5f8629f-6dc8-4f29-a1b7-81663d1e1a51",
              "sourceStep": "/api/3/workflow_steps/c2e6cb54-8213-4f30-a6fc-b53712ad94e5",
              "label": null,
              "isExecuted": false,
              "uuid": "d8694b73-133d-4a90-baa1-cb3e987e1de2"
            },
            {
              "@type": "WorkflowRoute",
              "name": "Compute Anomali Summary -> Is Malicious",
              "targetStep": "/api/3/workflow_steps/3e687780-5440-4b00-a419-c23279ad838e",
              "sourceStep": "/api/3/workflow_steps/d4f40f92-4761-416c-9fe9-741116b8b719",
              "label": null,
              "isExecuted": false,
              "uuid": "dcf2a891-206b-42b8-85c6-d44b2413e961"
            },
            {
              "@type": "WorkflowRoute",
              "name": "Get Domain Reputation from MxToolbox -> Compute MxToolbox Summary",
              "targetStep": "/api/3/workflow_steps/c1e368b1-ad55-4820-8f77-ea7992edb190",
              "sourceStep": "/api/3/workflow_steps/d0bae75f-5a3b-45a3-956c-6dd79b98e53a",
              "label": null,
              "isExecuted": false,
              "uuid": "e775a928-6478-40ae-8155-2846a20cedb9"
            },
            {
              "@type": "WorkflowRoute",
              "name": "Get Domain Reputation from Fortinet Web Filter -> Compute Fortinet Web Filter Summary",
              "targetStep": "/api/3/workflow_steps/ccb55494-0993-41c1-87e2-8716201f1e47",
              "sourceStep": "/api/3/workflow_steps/d2b49e99-afbc-42e6-ba09-c4c2aa3cfd71",
              "label": null,
              "isExecuted": false,
              "uuid": "ec341a55-a042-4878-8d2d-19ea22806883"
            },
            {
              "@type": "WorkflowRoute",
              "name": "Copy  of Compute VT Summary -> Is Malicious",
              "targetStep": "/api/3/workflow_steps/3e687780-5440-4b00-a419-c23279ad838e",
              "sourceStep": "/api/3/workflow_steps/ac8bc8d0-6607-460b-ab63-aa2e947bc8ef",
              "label": null,
              "isExecuted": false,
              "uuid": "fe48a9dc-8958-43f9-988e-5869e2cc03e1"
            },
            {
              "@type": "WorkflowRoute",
              "name": "Compute AV OTX Summary -> Is Malicious",
              "targetStep": "/api/3/workflow_steps/3e687780-5440-4b00-a419-c23279ad838e",
              "sourceStep": "/api/3/workflow_steps/2a86f387-914c-4c91-901a-3c7e2c7048f9",
              "label": null,
              "isExecuted": false,
              "uuid": "fed7fdd5-088d-4a30-9833-e249e32f6f88"
            }
          ],
          "priority": null,
          "uuid": "96692746-d039-419c-aa34-d48fdb5bc8fd",
          "id": 82,
          "createUser": "/api/3/people/3451141c-bac6-467c-8d72-85e0fab569ce",
          "createDate": 1649319945.016554,
          "modifyUser": "/api/3/people/3451141c-bac6-467c-8d72-85e0fab569ce",
          "modifyDate": 1649319945.016554,
          "owners": [],
          "isPrivate": false,
          "deletedAt": null,
          "importedBy": [
            {
              "apiName": "sOARFramework",
              "name": "SOAR Framework",
              "version": "1.0.0"
            }
          ],
          "recordTags": [
            "Enrichment"
          ]
        }
      ]
    }
  ],
  "exported_tags": [
    "Enrichment"
  ]
}