{
    "@context": "\/api\/3\/contexts\/Role",
    "@id": "\/api\/3\/roles\/21d7a7c6-9d68-438f-b732-e8950c5f745b",
    "@type": "Role",
    "description": "Essentially the root user, use carefully",
    "name": "Full App Permissions",
    "modulePermissions": [
        {
            "@id": "\/api\/3\/module_permissions\/2908b74a-e051-360f-bd62-b5e703116218",
            "@type": "ModulePermission",
            "canCreate": false,
            "canExecute": false,
            "canRead": true,
            "canUpdate": false,
            "canDelete": false,
            "fieldPermissions": [],
            "module": "application",
            "uuid": "2908b74a-e051-360f-bd62-b5e703116218"
        },
        {
            "@id": "\/api\/3\/module_permissions\/a531dfdb-2089-3ea1-9864-ca54c2d30c74",
            "@type": "ModulePermission",
            "canCreate": true,
            "canExecute": true,
            "canRead": true,
            "canUpdate": true,
            "canDelete": true,
            "fieldPermissions": [],
            "module": "workflows",
            "uuid": "a531dfdb-2089-3ea1-9864-ca54c2d30c74"
        },
        {
            "@id": "\/api\/3\/module_permissions\/eaaa9fdd-e591-3b76-ab88-cee6508faffb",
            "@type": "ModulePermission",
            "canCreate": true,
            "canExecute": false,
            "canRead": true,
            "canUpdate": true,
            "canDelete": true,
            "fieldPermissions": [],
            "module": "files",
            "uuid": "eaaa9fdd-e591-3b76-ab88-cee6508faffb"
        },
        {
            "@id": "\/api\/3\/module_permissions\/0871593a-6e25-3f7c-b25b-5da23c477d69",
            "@type": "ModulePermission",
            "canCreate": true,
            "canExecute": false,
            "canRead": true,
            "canUpdate": true,
            "canDelete": false,
            "fieldPermissions": [],
            "module": "activities",
            "uuid": "0871593a-6e25-3f7c-b25b-5da23c477d69"
        },
        {
            "@id": "\/api\/3\/module_permissions\/50446a00-667f-3c9b-86df-25473d9f0a44",
            "@type": "ModulePermission",
            "canCreate": true,
            "canExecute": false,
            "canRead": true,
            "canUpdate": true,
            "canDelete": true,
            "fieldPermissions": [],
            "module": "reporting",
            "uuid": "50446a00-667f-3c9b-86df-25473d9f0a44"
        },
        {
            "@id": "\/api\/3\/module_permissions\/178cd3c2-8c60-3ed3-b97c-15eca9756f95",
            "@type": "ModulePermission",
            "canCreate": true,
            "canExecute": false,
            "canRead": true,
            "canUpdate": true,
            "canDelete": true,
            "fieldPermissions": [],
            "module": "appliances",
            "uuid": "178cd3c2-8c60-3ed3-b97c-15eca9756f95"
        },
        {
            "@id": "\/api\/3\/module_permissions\/8ad9679e-7cfc-3f82-aeae-b1d7178afdf7",
            "@type": "ModulePermission",
            "canCreate": true,
            "canExecute": false,
            "canRead": true,
            "canUpdate": true,
            "canDelete": true,
            "fieldPermissions": [],
            "module": "attachments",
            "uuid": "8ad9679e-7cfc-3f82-aeae-b1d7178afdf7"
        },
        {
            "@id": "\/api\/3\/module_permissions\/23816176-c9cd-3384-8942-54ff8b237535",
            "@type": "ModulePermission",
            "canCreate": true,
            "canExecute": false,
            "canRead": true,
            "canUpdate": true,
            "canDelete": true,
            "fieldPermissions": [],
            "module": "comments",
            "uuid": "23816176-c9cd-3384-8942-54ff8b237535"
        },
        {
            "@id": "\/api\/3\/module_permissions\/64579f09-382d-3cf3-bbe6-f1cb3df90292",
            "@type": "ModulePermission",
            "canCreate": true,
            "canExecute": false,
            "canRead": true,
            "canUpdate": true,
            "canDelete": true,
            "fieldPermissions": [],
            "module": "companies",
            "uuid": "64579f09-382d-3cf3-bbe6-f1cb3df90292"
        },
        {
            "@id": "\/api\/3\/module_permissions\/1ac4376e-beab-3844-972a-a4c794314c75",
            "@type": "ModulePermission",
            "canCreate": true,
            "canExecute": false,
            "canRead": true,
            "canUpdate": true,
            "canDelete": true,
            "fieldPermissions": [],
            "module": "people",
            "uuid": "1ac4376e-beab-3844-972a-a4c794314c75"
        },
        {
            "@id": "\/api\/3\/module_permissions\/10b76963-2603-3001-952b-4a478dc8a406",
            "@type": "ModulePermission",
            "canCreate": true,
            "canExecute": false,
            "canRead": true,
            "canUpdate": true,
            "canDelete": true,
            "fieldPermissions": [],
            "module": "fsr_queues",
            "uuid": "10b76963-2603-3001-952b-4a478dc8a406"
        },
        {
            "@id": "\/api\/3\/module_permissions\/b625a8fa-16c9-3cab-9a3a-dea2d664d1e8",
            "@type": "ModulePermission",
            "canCreate": true,
            "canExecute": false,
            "canRead": true,
            "canUpdate": true,
            "canDelete": true,
            "fieldPermissions": [],
            "module": "shifts",
            "uuid": "b625a8fa-16c9-3cab-9a3a-dea2d664d1e8"
        },
        {
            "@id": "\/api\/3\/module_permissions\/464a93c9-e41e-3fd0-8f8f-d5e89cee320b",
            "@type": "ModulePermission",
            "canCreate": true,
            "canExecute": false,
            "canRead": true,
            "canUpdate": true,
            "canDelete": true,
            "fieldPermissions": [],
            "module": "tasks",
            "uuid": "464a93c9-e41e-3fd0-8f8f-d5e89cee320b"
        },
        {
            "@id": "\/api\/3\/module_permissions\/3894accf-5c9f-3324-adf2-4174d5ac3f43",
            "@type": "ModulePermission",
            "canCreate": true,
            "canExecute": true,
            "canRead": true,
            "canUpdate": true,
            "canDelete": true,
            "fieldPermissions": [],
            "module": "connectors",
            "uuid": "3894accf-5c9f-3324-adf2-4174d5ac3f43"
        },
        {
            "@id": "\/api\/3\/module_permissions\/2724ec8e-5be5-35c2-8aa3-6da824df8d72",
            "@type": "ModulePermission",
            "canCreate": true,
            "canExecute": false,
            "canRead": true,
            "canUpdate": true,
            "canDelete": true,
            "fieldPermissions": [],
            "module": "tenants",
            "uuid": "2724ec8e-5be5-35c2-8aa3-6da824df8d72"
        },
        {
            "@id": "\/api\/3\/module_permissions\/a4f301c1-4684-3af8-be5c-d5c7064907da",
            "@type": "ModulePermission",
            "canCreate": true,
            "canExecute": false,
            "canRead": true,
            "canUpdate": true,
            "canDelete": true,
            "fieldPermissions": [],
            "module": "routers",
            "uuid": "a4f301c1-4684-3af8-be5c-d5c7064907da"
        },
        {
            "@id": "\/api\/3\/module_permissions\/9b489b07-aab8-33cf-b7e1-982ac97ee850",
            "@type": "ModulePermission",
            "canCreate": true,
            "canExecute": false,
            "canRead": true,
            "canUpdate": true,
            "canDelete": true,
            "fieldPermissions": [],
            "module": "email_templates",
            "uuid": "9b489b07-aab8-33cf-b7e1-982ac97ee850"
        },
        {
            "@id": "\/api\/3\/module_permissions\/5a8d88c0-c634-3490-8388-49c84d3977c6",
            "@type": "ModulePermission",
            "canCreate": true,
            "canExecute": false,
            "canRead": true,
            "canUpdate": true,
            "canDelete": true,
            "fieldPermissions": [],
            "module": "schedules",
            "uuid": "5a8d88c0-c634-3490-8388-49c84d3977c6"
        },
        {
            "@id": "\/api\/3\/module_permissions\/3379a873-8298-3929-b0ef-dd4085e6e060",
            "@type": "ModulePermission",
            "canCreate": true,
            "canExecute": false,
            "canRead": true,
            "canUpdate": true,
            "canDelete": true,
            "fieldPermissions": [],
            "module": "approvals",
            "uuid": "3379a873-8298-3929-b0ef-dd4085e6e060"
        },
        {
            "@id": "\/api\/3\/module_permissions\/c1464bf2-4314-3f0b-b6c2-2eb2db40c053",
            "@type": "ModulePermission",
            "canCreate": true,
            "canExecute": false,
            "canRead": true,
            "canUpdate": true,
            "canDelete": true,
            "fieldPermissions": [],
            "module": "saved_reports",
            "uuid": "c1464bf2-4314-3f0b-b6c2-2eb2db40c053"
        },
        {
            "@id": "\/api\/3\/module_permissions\/5bd73593-8b96-300d-9125-3602ca994191",
            "@type": "ModulePermission",
            "canCreate": true,
            "canExecute": false,
            "canRead": true,
            "canUpdate": true,
            "canDelete": true,
            "fieldPermissions": [],
            "module": "dashboard",
            "uuid": "5bd73593-8b96-300d-9125-3602ca994191"
        },
        {
            "@id": "\/api\/3\/module_permissions\/67de2883-a7b0-3260-bb2a-67d3ffa3dc40",
            "@type": "ModulePermission",
            "canCreate": false,
            "canExecute": false,
            "canRead": true,
            "canUpdate": false,
            "canDelete": false,
            "fieldPermissions": [],
            "module": "security",
            "uuid": "67de2883-a7b0-3260-bb2a-67d3ffa3dc40"
        },
        {
            "@id": "\/api\/3\/module_permissions\/5f21c981-fed4-3762-a666-8f5d7a6b25fe",
            "@type": "ModulePermission",
            "canCreate": true,
            "canExecute": false,
            "canRead": true,
            "canUpdate": true,
            "canDelete": true,
            "fieldPermissions": [],
            "module": "agents",
            "uuid": "5f21c981-fed4-3762-a666-8f5d7a6b25fe"
        },
        {
            "@id": "\/api\/3\/module_permissions\/d12db338-ba01-35d7-aea0-ad53205b857d",
            "@type": "ModulePermission",
            "canCreate": true,
            "canExecute": true,
            "canRead": true,
            "canUpdate": true,
            "canDelete": true,
            "fieldPermissions": [],
            "module": "widgets",
            "uuid": "d12db338-ba01-35d7-aea0-ad53205b857d"
        },
        {
            "@id": "\/api\/3\/module_permissions\/b641c7bb-eb49-36f1-9e15-31be4b247bdf",
            "@type": "ModulePermission",
            "canCreate": true,
            "canExecute": false,
            "canRead": true,
            "canUpdate": true,
            "canDelete": true,
            "fieldPermissions": [],
            "module": "data_archival",
            "uuid": "b641c7bb-eb49-36f1-9e15-31be4b247bdf"
        },
        {
            "@id": "\/api\/3\/module_permissions\/cd29ba7a-f919-3e02-91d5-c1f554987190",
            "@type": "ModulePermission",
            "canCreate": true,
            "canExecute": false,
            "canRead": true,
            "canUpdate": true,
            "canDelete": true,
            "fieldPermissions": [],
            "module": "rules",
            "uuid": "cd29ba7a-f919-3e02-91d5-c1f554987190"
        },
        {
            "@id": "\/api\/3\/module_permissions\/2b3c32fc-8a0e-3300-80f9-5956874801dd",
            "@type": "ModulePermission",
            "canCreate": true,
            "canExecute": true,
            "canRead": true,
            "canUpdate": true,
            "canDelete": true,
            "fieldPermissions": [],
            "module": "solutionpacks",
            "uuid": "2b3c32fc-8a0e-3300-80f9-5956874801dd"
        },
        {
            "@id": "\/api\/3\/module_permissions\/dcca7fe9-a93d-3a87-9c65-96116e63baa2",
            "@type": "ModulePermission",
            "canCreate": false,
            "canExecute": false,
            "canRead": true,
            "canUpdate": false,
            "canDelete": false,
            "fieldPermissions": [],
            "module": "marketplace",
            "uuid": "dcca7fe9-a93d-3a87-9c65-96116e63baa2"
        },
        {
            "@id": "\/api\/3\/module_permissions\/53a45a96-d22a-494c-9870-dc7916706e60",
            "@type": "ModulePermission",
            "canCreate": true,
            "canExecute": true,
            "canRead": true,
            "canUpdate": true,
            "canDelete": true,
            "fieldPermissions": [],
            "module": "alerts",
            "uuid": "53a45a96-d22a-494c-9870-dc7916706e60"
        },
        {
            "@id": "\/api\/3\/module_permissions\/13ab6679-52d9-4b0d-af25-25ee0eed36be",
            "@type": "ModulePermission",
            "canCreate": true,
            "canExecute": true,
            "canRead": true,
            "canUpdate": true,
            "canDelete": true,
            "fieldPermissions": [],
            "module": "announcements",
            "uuid": "13ab6679-52d9-4b0d-af25-25ee0eed36be"
        },
        {
            "@id": "\/api\/3\/module_permissions\/27ac651f-a01f-473a-83c3-d528f7790cc4",
            "@type": "ModulePermission",
            "canCreate": true,
            "canExecute": true,
            "canRead": true,
            "canUpdate": true,
            "canDelete": true,
            "fieldPermissions": [],
            "module": "assets",
            "uuid": "27ac651f-a01f-473a-83c3-d528f7790cc4"
        },
        {
            "@id": "\/api\/3\/module_permissions\/9ac33792-c7b6-49b4-9122-23a752b3a40b",
            "@type": "ModulePermission",
            "canCreate": true,
            "canExecute": true,
            "canRead": true,
            "canUpdate": true,
            "canDelete": true,
            "fieldPermissions": [],
            "module": "campaigns",
            "uuid": "9ac33792-c7b6-49b4-9122-23a752b3a40b"
        },
        {
            "@id": "\/api\/3\/module_permissions\/dbae4dd6-946d-4d1a-8dab-a0d92eab1c92",
            "@type": "ModulePermission",
            "canCreate": true,
            "canExecute": true,
            "canRead": true,
            "canUpdate": true,
            "canDelete": true,
            "fieldPermissions": [],
            "module": "communication",
            "uuid": "dbae4dd6-946d-4d1a-8dab-a0d92eab1c92"
        },
        {
            "@id": "\/api\/3\/module_permissions\/ec74db9e-424e-43ae-aff9-9aa8f3c7a637",
            "@type": "ModulePermission",
            "canCreate": true,
            "canExecute": true,
            "canRead": true,
            "canUpdate": true,
            "canDelete": true,
            "fieldPermissions": [],
            "module": "events",
            "uuid": "ec74db9e-424e-43ae-aff9-9aa8f3c7a637"
        },
        {
            "@id": "\/api\/3\/module_permissions\/2ac82360-7548-4779-9406-dd69fa549e44",
            "@type": "ModulePermission",
            "canCreate": true,
            "canExecute": true,
            "canRead": true,
            "canUpdate": true,
            "canDelete": true,
            "fieldPermissions": [],
            "module": "hunt",
            "uuid": "2ac82360-7548-4779-9406-dd69fa549e44"
        },
        {
            "@id": "\/api\/3\/module_permissions\/219602aa-e2f6-4219-9561-9825f5a51cbf",
            "@type": "ModulePermission",
            "canCreate": true,
            "canExecute": true,
            "canRead": true,
            "canUpdate": true,
            "canDelete": true,
            "fieldPermissions": [],
            "module": "incidents",
            "uuid": "219602aa-e2f6-4219-9561-9825f5a51cbf"
        },
        {
            "@id": "\/api\/3\/module_permissions\/9a72e6d9-0a61-4ced-a0bc-93b0ba1150d8",
            "@type": "ModulePermission",
            "canCreate": true,
            "canExecute": true,
            "canRead": true,
            "canUpdate": true,
            "canDelete": true,
            "fieldPermissions": [],
            "module": "indicators",
            "uuid": "9a72e6d9-0a61-4ced-a0bc-93b0ba1150d8"
        },
        {
            "@id": "\/api\/3\/module_permissions\/6cc7ccd5-14ae-4b40-a926-489ea9a88941",
            "@type": "ModulePermission",
            "canCreate": true,
            "canExecute": true,
            "canRead": true,
            "canUpdate": true,
            "canDelete": true,
            "fieldPermissions": [],
            "module": "warrooms",
            "uuid": "6cc7ccd5-14ae-4b40-a926-489ea9a88941"
        }
    ],
    "uuid": "21d7a7c6-9d68-438f-b732-e8950c5f745b"
}