{
    "@context": "\/api\/3\/contexts\/SystemViewTemplate",
    "@type": "SystemViewTemplate",
    "type": "rows",
    "config": {
        "rows": [
            {
                "columns": [
                    {
                        "widgets": [
                            {
                                "type": "primaryDetail",
                                "config": {
                                    "wid": "3e7048c4-63f5-44bf-89bb-d2be9c59a0cf",
                                    "idField": "id",
                                    "picklistFieldReadOnly": true,
                                    "titleFieldReadOnly": false,
                                    "titleFieldLinky": false,
                                    "featuredRelationship": {
                                        "field": null,
                                        "preText": "Under Investigation In",
                                        "query": null,
                                        "statusField": null,
                                        "sort": []
                                    },
                                    "picklistField": "announcementType",
                                    "titleField": "title"
                                }
                            }
                        ],
                        "style": "col-lg-12"
                    }
                ],
                "wid": "cd1bee28-49a0-4c96-9fed-f71199d077ca",
                "_collapsed": false
            },
            {
                "columns": [
                    {
                        "widgets": [
                            {
                                "type": "editableFormGroup",
                                "config": {
                                    "wid": "f643fede-968e-4058-a561-9a542ca5bf9a",
                                    "rows": [
                                        {
                                            "columns": [
                                                {
                                                    "fields": [
                                                        {
                                                            "name": "title",
                                                            "highlightMode": true,
                                                            "linky": true,
                                                            "readOnly": false
                                                        },
                                                        {
                                                            "name": "description",
                                                            "highlightMode": true,
                                                            "linky": true,
                                                            "readOnly": false
                                                        },
                                                        {
                                                            "name": "notifyOnEmail",
                                                            "highlightMode": true,
                                                            "linky": true,
                                                            "readOnly": false
                                                        }
                                                    ]
                                                }
                                            ]
                                        }
                                    ]
                                }
                            }
                        ],
                        "style": "col-lg-12"
                    }
                ],
                "wid": "28d2567b-bb12-4364-b98f-3eb85c7fe85a",
                "_collapsed": false
            },
            {
                "columns": [
                    {
                        "widgets": [
                            {
                                "type": "tabs",
                                "config": {
                                    "tabs": [
                                        {
                                            "title": "Correlations",
                                            "widget": {
                                                "type": "relationship.subtab",
                                                "config": {
                                                    "excludes": [
                                                        "notes",
                                                        "comments",
                                                        "userOwners",
                                                        "attachments"
                                                    ],
                                                    "wid": "eb1bfffe-d356-48f2-877f-12e8ae672ccd"
                                                }
                                            },
                                            "show": true,
                                            "icon": "fa fa-exchange"
                                        }
                                    ],
                                    "wid": "849400b1-07e3-49e8-8169-86b82e49c2c7"
                                }
                            }
                        ],
                        "style": "col-lg-12"
                    }
                ],
                "wid": "c25c5683-d6ea-45b2-ac0f-2ce700bfa2d5",
                "_collapsed": false
            }
        ],
        "wid": "349ed4a7-ccb1-4623-936d-552d98186642",
        "actionButtons": []
    },
    "uuid": "modules-announcements-detail"
}